Workbook

Sheet 00 Read Me
A1: ExamPrep AI — Student Evaluation Platform
A2: Module-wise Construction Blueprint | Version 1.4 | 05 Sep 2026 | 17 tabs, 122 features
A4: What this workbook is
A5: A build plan, not code. It converts the ExamPrep AI tutor specification (paper generation, uploaded-paper evaluation, concept tracking, remediation, weekly summaries) plus the existing Grok prototype into 22 buildable modules with features, data model, APIs, screens, AI functions, effort and a phased roadmap.
A7: Source material behind the plan
A8: 1. The ExamPrep AI role specification (7 sections: paper generation, evaluation protocol, concept tracking, session memory, teaching rules, weekly summary, final directive).
A9: 2. The uploaded Grok prototype (grok-workspace.zip): TanStack Start + React 19 + Tailwind v4 + shadcn/ui, better-auth, Postgres (Neon) / PGlite via Kysely, Zustand persist, deployed on Vercel. It ships a hardcoded Class-7 NCERT Ganita Prakash curriculum (15 chapters), ~75 questions, a mastery engine, and practice / exam / learn / mastery routes.
A10: 3. The live coaching project's diagnostic framework: Actual Score vs Knowledge Score, Delivery Gap, error patterns P1-P6, presentation habits H1-H10.
A12: How to use each tab
A13: 01 Product Scope | B13: In scope / out of scope / personas / success metrics. Agree this first — it is the contract for everything below.
A14: 02 Module Master | B14: The 22 modules. Effort, feature count and % complete auto-roll from tab 03. This is your weekly status page.
A15: 03 Feature Backlog | B15: 111 features with user story, acceptance criteria, effort and sprint. This is what you hand to a developer or to Claude Code, one row at a time.
A16: 04 Data Model | B16: 26 tables with key columns and relations. Build this before any UI.
A17: 05 API Endpoints | B17: 38 routes with auth level and payload shape.
A18: 06 Screens & Routes | B18: 24 screens mapped to modules and roles.
A19: 07 AI Layer | B19: 12 AI functions with model choice, prompt inputs, output contract, guardrails and fallback. The riskiest and most valuable tab.
A20: 08 Gap Analysis | B20: What the Grok prototype already gives you vs what must be built. Reuse column tells you what to keep.
A21: 09 Tech Stack | B21: Locked technology decisions with rationale and alternatives rejected.
A22: 10 Roadmap | B22: 5 phases with dates driven from the Project Start Date cell. Change that one cell and all dates move.
A23: 11 Risks | B23: 14 risks scored by probability x impact with owner and mitigation.
A24: 12 QA & Test Plan | B24: 22 test scenarios by module, including the accuracy tests that matter most (OCR, AI grading, Telugu script).
A25: 13 Effort Summary | B25: Rolled-up effort by phase and priority, converted to calendar weeks using the velocity assumptions at the top.
A27: Legend
A28: Blue text | B28: An input you can change. All other cells are text or formulas.
A29: Yellow fill | B29: Key assumption. Verify before committing to a date.
A30: Priority | B30: P0 = MVP blocker. P1 = needed for a usable v1. P2 = valuable. P3 = later / optional.
A31: Status | B31: Not Started / In Progress / Blocked / Done. Type it in column J of tab 03; tab 02 and 13 recalculate.
A32: Effort | B32: Person-days for one mid-level full-stack developer working with an AI coding assistant. Estimates, not quotes.
A34: Decisions still open (answer before Phase 1 starts)
A35: 1. Single-family tool or multi-tenant product? | B35: Changes M02, M20 and M21 substantially. Plan currently assumes: build single-family first, keep the schema multi-tenant-ready.
A36: 2. Which subjects at launch? | B36: Plan assumes Maths + Science in Phase 1, Social + Telugu in Phase 2. Telugu carries font, script and grammar-tagging cost (M18).
A37: 3. Handwritten evaluation: photo upload or typed transcription? | B37: Photo + vision OCR (M10) is the honest answer but the least reliable. Plan keeps typed fallback always available.
A38: 4. Does the student attempt papers on screen, or on paper then upload? | B38: Plan supports both. On-screen (M08) is cheaper and auto-scored; paper-then-upload (M10) is what actually reflects exam conditions.
A39: 5. Board coverage: CBSE only, or CBSE + AP/TS State? | B39: Affects M04 blueprint engine. Plan assumes CBSE-style blueprints first, State Board added as a blueprint record, not new code.

Sheet 01 Product Scope
A1: 01 Product Scope, Personas and Success Metrics
A3: Category | B3: Item | C3: Detail | D3: Status / Priority
A4: Vision | B4: One sentence | C4: A web app that generates syllabus-exact question papers, evaluates the student's attempt question-by-question, diagnoses whether each lost mark is a knowledge gap or a delivery habit, and tracks every concept until it is mastered. | D4: Agreed
A5: Primary persona | B5: Parent / coach | C5: Sets up the child, requests papers, uploads the written attempt, reads the diagnosis, receives one concrete action per session. Not a teacher; needs plain language. | D5: Agreed
A6: Secondary persona | B6: Student (Class 6-10) | C6: Takes practice sets and timed mocks on screen, sees mastery rings and remediation drills. Must never feel graded harshly in tone. | D6: Agreed
A7: Tertiary persona | B7: Tutor / school teacher | C7: Multi-student console, bulk paper generation, class-level weak-concept heatmap. Phase 4. | D7: Deferred
A8: In scope | B8: Paper generation | C8: Blueprint-driven papers per subject/chapter/marks/duration, with sections A-D, Bloom distribution, concept tags, answer key, marking scheme, concept coverage table, printable A4 PDF. | D8: P0
A9: In scope | B9: Attempt capture | C9: On-screen attempt (auto-scored) AND photo/scan upload of a handwritten attempt (AI-assisted evaluation with human confirm). | D9: P0/P1
A10: In scope | B10: Evaluation | C10: Per-question marks, error classification, Actual vs Knowledge score, Delivery Gap, habit observations. | D10: P0
A11: In scope | B11: Tracking | C11: Cumulative concept tracker with trend arrows, priority flag rules, auto-generated mini revision tests, weekly summary. | D11: P0
A12: In scope | B12: Remediation | C12: 4-step protocol per weak concept: refresher, 2 solved examples, 3 practice questions, upload-and-evaluate loop. | D12: P1
A13: In scope | B13: Subjects | C13: Maths and Science at launch; Social Studies and Telugu in Phase 2 (Telugu needs script + grammar tagging). | D13: P0/P1
A14: Out of scope v1 | B14: Live video tutoring | C14: No synchronous teaching, no video calls. | D14: Excluded
... A26: Constraint | B26: Offline reality | C26: The printed PDF is the primary artefact. The app must remain useful for a family that prints, writes by hand and uploads photos. | D26: Design rule

Sheet 02 Module Master
A1: 02 Module Master — counts and effort roll up automatically from tab 03
A3: Module ID | B3: Module | C3: Phase | D3: Purpose | E3: Key Deliverable | F3: Depends On | G3: Priority | H3: Notes / Reuse | I3: Features | J3: Est. Days | K3: Done | L3: % Complete
A4: M01 | B4: Foundation & Infrastructure | C4: P0 Foundation | D4: Repo, environments, CI, Vercel projects, error tracking, secrets. | E4: Deployable skeleton with preview + prod environments | F4: - | G4: P0 | H4: Reuse Grok scaffold heavily | I4: =COUNTIF('03 Feature Backlog'!$A:$A,$A4) | J4: =SUMIF('03 Feature Backlog'!$A:$A,$A4,'03 Feature Backlog'!$H:$H) | K4: =COUNTIFS('03 Feature Backlog'!$A:$A,$A4,'03 Feature Backlog'!$J:$J,"Done") | L4: =IFERROR(K4/I4,0)
A5: M02 | B5: Auth, Roles & Household | C5: P0 Foundation | D5: Sign-in, parent/student/admin roles, one household with many students. | E5: Role-gated routing and student switching | F5: M01 | G5: P0 | H5: better-auth already wired in prototype | I5: =COUNTIF('03 Feature Backlog'!$A:$A,$A5) | J5: =SUMIF('03 Feature Backlog'!$A:$A,$A5,'03 Feature Backlog'!$H:$H) | K5: =COUNTIFS('03 Feature Backlog'!$A:$A,$A5,'03 Feature Backlog'!$J:$J,"Done") | L5: =IFERROR(K5/I5,0)
A6: M03 | B6: Database & Migrations | C6: P0 Foundation | D6: Postgres schema, migration runner, seed scripts, backup policy. | E6: Versioned schema covering all 26 tables | F6: M01 | G6: P0 | H6: Prototype has Kysely + migration script | I6: =COUNTIF('03 Feature Backlog'!$A:$A,$A6) | J6: =SUMIF('03 Feature Backlog'!$A:$A,$A6,'03 Feature Backlog'!$H:$H) | K6: =COUNTIFS('03 Feature Backlog'!$A:$A,$A6,'03 Feature Backlog'!$J:$J,"Done") | L6: =IFERROR(K6/I6,0)
A7: M04 | B7: Curriculum & Syllabus Engine | C7: P1 Core | D7: Board > class > subject > chapter > concept hierarchy with explicit in-scope and out-of-scope text per chapter. | E7: Admin-editable syllabus tree with scope guards | F7: M03 | G7: P0 | H7: Prototype hardcodes this in TypeScript — must move to DB | I7: =COUNTIF('03 Feature Backlog'!$A:$A,$A7) | J7: =SUMIF('03 Feature Backlog'!$A:$A,$A7,'03 Feature Backlog'!$H:$H) | K7: =COUNTIFS('03 Feature Backlog'!$A:$A,$A7,'03 Feature Backlog'!$J:$J,"Done") | L7: =IFERROR(K7/I7,0)
A8: M05 | B8: Question Bank | C8: P1 Core | D8: Questions with concept, Bloom, difficulty, marks, type, options, answer, hint, step-marks, diagram, language. | E8: CRUD + bulk import + duplicate detection | F8: M04 | G8: P0 | H8: 75 seed questions exist | I8: =COUNTIF('03 Feature Backlog'!$A:$A,$A8) | J8: =SUMIF('03 Feature Backlog'!$A:$A,$A8,'03 Feature Backlog'!$H:$H) | K8: =COUNTIFS('03 Feature Backlog'!$A:$A,$A8,'03 Feature Backlog'!$J:$J,"Done") | L8: =IFERROR(K8/I8,0)
A9: M06 | B9: Paper Blueprint & Generator | C9: P1 Core | D9: Blueprint records (sections, marks, counts, Bloom mix, choice rules) + weighted selection 40/40/20 from the mastery log. | E9: One-click paper honouring blueprint and weak-concept weighting | F9: M05, M12 | G9: P0 | H9: Core differentiator — nothing in prototype | I9: =COUNTIF('03 Feature Backlog'!$A:$A,$A9) | J9: =SUMIF('03 Feature Backlog'!$A:$A,$A9,'03 Feature Backlog'!$H:$H) | K9: =COUNTIFS('03 Feature Backlog'!$A:$A,$A9,'03 Feature Backlog'!$J:$J,"Done") | L9: =IFERROR(K9/I9,0)
A10: M07 | B10: Paper Rendering & Export | C10: P1 Core | D10: Themed HTML + print-ready A4 PDF with rough-work column, answer key, marking scheme, concept coverage table. | E10: PDF identical to school paper format | F10: M06 | G10: P0 | H10: Server-side PDF; template engine needed | I10: =COUNTIF('03 Feature Backlog'!$A:$A,$A10) | J10: =SUMIF('03 Feature Backlog'!$A:$A,$A10,'03 Feature Backlog'!$H:$H) | K10: =COUNTIFS('03 Feature Backlog'!$A:$A,$A10,'03 Feature Backlog'!$J:$J,"Done") | L10: =IFERROR(K10/I10,0)
A11: M08 | B11: Online Test Engine | C11: P1 Core | D11: Timed on-screen attempt, autosave, resume, section navigation, review-before-submit. | E11: Attempt captured with per-question timing | F11: M05 | G11: P0 | H11: Prototype has a basic exam.take flow | I11: =COUNTIF('03 Feature Backlog'!$A:$A,$A11) | J11: =SUMIF('03 Feature Backlog'!$A:$A,$A11,'03 Feature Backlog'!$H:$H) | K11: =COUNTIFS('03 Feature Backlog'!$A:$A,$A11,'03 Feature Backlog'!$J:$J,"Done") | L11: =IFERROR(K11/I11,0)
A12: M09 | B12: Auto-Evaluation Engine | C12: P1 Core | D12: Objective auto-scoring, subjective rubric scoring with AI, step-mark allocation, human override. | E12: Marks + error type per question, always overridable | F12: M08 | G12: P0 | H12: Prototype scores MCQ/fill only | I12: =COUNTIF('03 Feature Backlog'!$A:$A,$A12) | J12: =SUMIF('03 Feature Backlog'!$A:$A,$A12,'03 Feature Backlog'!$H:$H) | K12: =COUNTIFS('03 Feature Backlog'!$A:$A,$A12,'03 Feature Backlog'!$J:$J,"Done") | L12: =IFERROR(K12/I12,0)
A13: M10 | B13: Upload & Handwriting OCR | C13: P2 Diagnostics | D13: Photo/PDF upload of written attempt, page-to-question mapping, vision extraction, ambiguity flagging. | E13: Handwritten paper converted to reviewable answers | F13: M09 | G13: P1 | H13: Highest technical risk | I13: =COUNTIF('03 Feature Backlog'!$A:$A,$A13) | J13: =SUMIF('03 Feature Backlog'!$A:$A,$A13,'03 Feature Backlog'!$H:$H) | K13: =COUNTIFS('03 Feature Backlog'!$A:$A,$A13,'03 Feature Backlog'!$J:$J,"Done") | L13: =IFERROR(K13/I13,0)
A14: M11 | B14: Diagnostic Engine | C14: P2 Diagnostics | D14: Actual vs Knowledge score, Delivery Gap, error patterns P1-P6, presentation habits H1-H10. | E14: Diagnosis report per paper | F14: M09 | G14: P0 | H14: The intellectual heart of the product | I14: =COUNTIF('03 Feature Backlog'!$A:$A,$A14) | J14: =SUMIF('03 Feature Backlog'!$A:$A,$A14,'03 Feature Backlog'!$H:$H) | K14: =COUNTIFS('03 Feature Backlog'!$A:$A,$A14,'03 Feature Backlog'!$J:$J,"Done") | L14: =IFERROR(K14/I14,0)
A15: M12 | B15: Concept Tracker & Mastery | C15: P1 Core | D15: Running per-concept log, trend arrows, priority flag rules, maintenance/retire rules. | E15: Cumulative tracker driving paper weighting | F15: M09 | G15: P0 | H15: Prototype mastery engine is a good base | I15: =COUNTIF('03 Feature Backlog'!$A:$A,$A15) | J15: =SUMIF('03 Feature Backlog'!$A:$A,$A15,'03 Feature Backlog'!$H:$H) | K15: =COUNTIFS('03 Feature Backlog'!$A:$A,$A15,'03 Feature Backlog'!$J:$J,"Done") | L15: =IFERROR(K15/I15,0)
... A25: M22 | B25: QA, Testing & Launch | C25: P4 Hardening | D25: Unit/integration/E2E, AI accuracy harness, UAT with real papers, launch checklist. | E25: Green suite + 20-paper accuracy benchmark | F25: All | G25: P0 | H25: Accuracy harness is non-negotiable | I25: =COUNTIF('03 Feature Backlog'!$A:$A,$A25) | J25: =SUMIF('03 Feature Backlog'!$A:$A,$A25,'03 Feature Backlog'!$H:$H) | K25: =COUNTIFS('03 Feature Backlog'!$A:$A,$A25,'03 Feature Backlog'!$J:$J,"Done") | L25: =IFERROR(K25/I25,0)
H26: TOTAL | I26: =SUM(I4:I25) | J26: =SUM(J4:J25) | K26: =SUM(K4:K25) | L26: =IFERROR(K26/I26,0)

Sheet 03 Feature Backlog
A1: 03 Feature Backlog — 132 features. Type Not Started / In Progress / Blocked / Done in column J.
A3: Module ID | B3: Feature ID | C3: Feature | D3: User Story | E3: Acceptance Criteria | F3: Priority | G3: Complexity | H3: Est. Days | I3: Sprint | J3: Status | K3: Notes
A4: M01 | B4: F001 | C4: Repo & monorepo setup | D4: As a developer I want a clean repo so that work is versioned and reviewable. | E4: Repo initialised, branch protection on main, PR template, conventional commits, README with local setup that works from a cold clone. | F4: P0 | G4: S | H4: 1 | I4: S1 | J4: Done | K4: Repo initialised, PR template + conventional-commit convention in place. GitHub remote set up (sathyaantham2-wq/examprep-ai-, pushed 2026-09-16). Branch protection on main now requires the Vercel status check to pass before merge (see F003).
A5: M01 | B5: F002 | C5: Environment & secrets management | D5: As a developer I want typed env vars so that misconfiguration fails loudly at boot. | E5: Zod-validated env schema; app refuses to start on missing keys; .env.example committed; secrets stored in Vercel, never in git. | F5: P0 | G5: S | H5: 1 | I5: S1 | J5: Done | K5: src/lib/env.ts: a single Zod schema for every env var actually read anywhere in the codebase (DATABASE_URL, BETTER_AUTH_SECRET/URL required; GOOGLE_CLIENT_ID/SECRET and ANTHROPIC_API_KEY optional, matching their documented graceful-degradation paths). Replaced every scattered process.env.X read (connection.ts, auth-pool.ts, auth.ts, ai-grading.ts) with this validated object. Verified live: booting with BETTER_AUTH_SECRET removed throws immediately with the exact missing key named, not a confusing failure deep in a request; booting normally still works, confirmed via a live dev-server request. .env.example already existed and now documents ANTHROPIC_API_KEY too. "Secrets stored in Vercel, never in git" -- .env is already gitignored (verified back in F001) and no secret has been committed at any point this project.
A6: M01 | B6: F003 | C6: Vercel preview + production pipeline | D6: As a team I want every PR to deploy a preview so that changes are reviewed live. | E6: PR opens a preview URL; main deploys to production; build fails block merge. | F6: P0 | G6: S | H6: 1 | I6: S1 | J6: Done | K6: Repo pushed to GitHub (sathyaantham2-wq/examprep-ai-) and connected to Vercel. Verified live: push to main deploys production, a real PR (#1) produced a real preview URL and merged cleanly. Branch protection on main now requires the examprep-ai Vercel check to pass before merge (set up 2026-09-16). One loose end, not blocking: a duplicate Vercel project (examprep-ai-, trailing hyphen) still exists from setup -- harmless (both point at the same repo/commits) but should be deleted via the Vercel dashboard when convenient; no delete capability was available via the connected Vercel MCP connector to do it directly.
A7: M01 | B7: F004 | C7: Error tracking & structured logging | D7: As a developer I want server errors captured so that failures are not silent. | E7: Sentry (or equivalent) capturing client + server errors with release tagging; request-scoped log IDs. | F7: P1 | G7: S | H7: 1 | I7: S2 | J7: Done | K7: No Sentry/error-tracking account exists in this dev environment, so error_log (migration 0060) is a self-hosted equivalent, wired the same way Sentry would be. Server: every route handler wrapped via wrapRouteHandlers() -- catches unhandled exceptions, writes one error_log row with a request-scoped UUID (request_id), echoes the same id back in the response header and body. Client: root error boundary (__root.tsx) + a window.onerror/unhandledrejection listener POST the same shape to the new public POST /api/errors route. release column tagged from VERCEL_GIT_COMMIT_SHA (set automatically by Vercel per deploy) -- Vercel-set env var added to env.ts. Verified: 8 unit/integration tests (error-log.test.ts, error-log.integration.test.ts) plus a full-suite regression run (376 tests, 66 files, all green) confirming the mechanical wrapRouteHandlers() rollout across all 65+ route files changed no existing route behaviour. Committed 8399dbb.
A8: M01 | B8: F005 | C8: Design system & theming | D8: As a user I want a consistent interface so that the app feels coherent. | E8: shadcn/ui + Tailwind tokens, light/dark, typography scale, print stylesheet defined once. | F8: P1 | G8: M | H8: 2 | I8: S2 | J8: In Progress | K8: shadcn/ui is now actually wired in (components.json was configured but nothing had been added yet) -- hand-written Button (5 variants: default/destructive/outline/secondary/ghost/link, 4 sizes) and Card (+ Header/Title/Description/Content/Footer) primitives now live at src/components/ui/, matching the existing "new-york" style config and using the pre-existing cn() helper. A ThemeProvider (next-themes, class-based, system-aware, SSR-safe via suppressHydrationWarning) wraps the whole app in __root.tsx, plus a working ThemeToggle component. A typography scale (.text-display/.text-h1/.text-h2/.text-h3/.text-body/.text-small/.text-caption) is defined once in src/styles.css for every future screen to reuse instead of ad-hoc text-* sizes. A print stylesheet (@media print) flattens colors to black-on-white, drops anything marked .no-print, and cleans up card borders/shadows for printouts -- this covers screens a parent might Ctrl+P directly (e.g. a report page), separate from the existing server-side Playwright PDF pipeline used for generated papers/reports. Also removed roughly 180 lines of dead, unreferenced "ocean/island" decorative CSS (sea-ink/lagoon/palm color variables, island-shell, feature-card, nav-link, site-footer classes) that had been sitting in styles.css since the initial scaffold but were never used by any actual component -- confirmed via grep before removing. The updated homepage (src/routes/index.tsx) exercises all of this (all four button variants, a card, the type scale, the theme toggle) and was verified by hand in a real running dev server: fetched the rendered HTML, confirmed the shadcn button/card classes and data-slot attributes are present, confirmed the inline theme-detection script runs and toggles the "dark" class correctly, confirmed the print media query and type-scale classes are in the served CSS bundle, and confirmed the old dead classes are gone from the served CSS. Full test suite (19 files / 119 tests) still passes after the change, tsc and eslint are clean. No dark-mode-aware redesign of any other screen exists yet (there's only the one placeholder route to redesign so far) -- this lays the foundation tokens/primitives down for the 24 screens in tab06 to build on, not a finished visual identity for the product. No Storybook or visual regression tooling, and no accessibility audit beyond what shadcn's defaults already provide. Marked In Progress rather than Done since a design system isn't really finished until more than one real screen has exercised it.
A9: M02 | B9: F006 | C9: Email/password + Google sign-in | D9: As a parent I want to sign in securely so that my child's data is private. | E9: better-auth with email+password and Google OAuth; verified email; session cookie httpOnly+secure; logout everywhere. | F9: P0 | G9: M | H9: 2 | I9: S1 | J9: Done | K9: better-auth mounted at /api/auth/$ (catch-all, src/routes/api/auth/$.ts). Email+password with required email verification (verified end-to-end: sign-up -> logged verification link -> verify-email -> sign-in). Google OAuth wired but conditional on GOOGLE_CLIENT_ID/SECRET, which are not set in dev -- needs real credentials before it is testable; the UI has no Google sign-in button yet for the same reason. Session cookie confirmed httpOnly+SameSite=Lax via curl; Secure is added automatically once BETTER_AUTH_URL is https in prod. Sign-out/session endpoints come from betterauth's own router, not hand-written. Resend (M16) does not exist yet, so verification emails are logged server-side, not delivered -- flagged, not silently faked. UI now exists -- see `/` (sign-in/sign-up) and `/onboarding` (add-student wizard), browser-verified end to end including the real email-verification link from the server log.
A10: M02 | B10: F007 | C10: Role model (parent / student / admin) | D10: As a parent I want my child to have a limited login so that they cannot edit marks. | E10: Role stored on user; route guards server-side, not just client; student role cannot access evaluation-override or admin routes. | F10: P0 | G10: M | H10: 3 | I10: S1 | J10: Done | K10: Role stored on users.role (parent/student/admin), assigned server-side only (better-auth additionalFields role/household_id have input:false; a signup payload cannot set them). src/lib/session.ts requireUser/requireRole enforce auth on the request itself. Verified live: unauthenticated request to GET /api/students -> 401; a directly-seeded student-role user -> 403 on GET and POST /api/students. No admin or evaluation-override route exists yet to test T01 literally against, but the same guard is what any future one will use. -- A parent-facing way to actually create a student's login now exists too (POST /api/students/:id/login + a small /onboarding UI) -- this was new scope, not this ticket's own AC, flagged to and approved by the user rather than silently added; see F010's note for the full context.
A11: M02 | B11: F008 | C11: Household & multi-student profiles | D11: As a parent with two children I want separate profiles so that data never mixes. | E11: Household owns N students; student switcher in header; every query scoped by student_id; switching cannot leak cached data. | F11: P0 | G11: M | H11: 3 | I11: S2 | J11: Done | K11: GET/POST /api/students and PATCH /api/students/:id (src/routes/api/students.ts, .../students/.ts), all household-scoped via studentsRepository (F013). Verified live with two separate parent signups: parent B's list is empty and never sees parent A's student; parent B's PATCH on parent A's student returns 404, not 403 or a leaked row. UI now exists -- see `/` (sign-in/sign-up) and `/onboarding` (lists existing students, form to add a new one with name/class/board/school/consent), browser-verified end to end including the real email-verification link from the server log. No student switcher in the header yet though -- that's a separate screen from the onboarding wizard and still doesn't exist. -- A parent-facing way to actually create a student's login now exists too (POST /api/students/:id/login + a small /onboarding UI) -- this was new scope, not this ticket's own AC, flagged to and approved by the user rather than silently added; see F010's note for the full context.
A12: M02 | B12: F009 | C12: Student profile fields | D12: As a coach I want class, board, school and roll number stored so that papers carry the right header. | E12: Profile: name, class, section, roll no, board, school, subjects active, target exam dates; used in paper header automatically. | F12: P0 | G12: S | H12: 1 | I12: S2 | J12: Done | K12: F008's schema already had name/class/section/roll_no/board/school/target_exams -- the real gap was that POST /api/students never accepted section or target_exams at creation, and PATCH /api/students/:id had no target_exams field at all, so a student's target exam dates could never be set or changed after creation (stuck at the hardcoded []). Both routes now accept target_exams as a validated {name, date}[] and POST accepts section too. 'subjects active' is intentionally not modelled: the whole product is single-subject today (CLAUDE.md's launch scope is CBSE Class 7 Maths only, and MATH-SEED is the only subject that has ever existed in this schema), so there is nothing yet for that field to distinguish -- revisit at the tab17 multi-subject rollout, not now. 'used in paper header automatically' already existed before this feature (F033's buildPaperHtml reads student.name/board/class). Verified live against the real dev DB (students-profile.integration.test.ts): create with section+target_exams, a partial PATCH that updates only target_exams without touching other fields, and a rejected malformed date. UI now exists too -- the /onboarding add-student wizard (name/class/board/school/consent checkbox) posts to this same route, browser-verified end to end.
A13: M02 | B13: F010 | C13: Parent-controlled student access | D13: As a parent I want to enable or disable my child's login so that I control screen time. | E13: Toggle per student; disabled student sees a friendly locked screen; parent always retains access. | F13: P2 | G13: S | H13: 1 | I13: S6 | J13: Done | K13: A gap was found while scoping the paper-attempt-start screen: no API or screen anywhere let a parent actually create a student's login -- every test fixture (createStudentSession in db/test-helpers.ts) inserted a student-role user + credential account directly into the database, so a real parent had no path to ever produce a working student login, which blocked the whole "student logs in and attempts a paper" loop from being demonstrable through real UI. This was new scope, not this ticket's own AC -- flagged explicitly per CLAUDE.md's "never invent a feature ID" rule, and the user chose to have it built now, clearly flagged. Closed via a new POST /api/students/:id/login route (parent/admin only, household-scoped, 404 on another household's student, creates a role:'student' user + credential account mirroring the test fixture, links students.user_id, rejects 409 on an existing login or a taken email, never returns the password hash) plus a small /onboarding UI (a "Create login" inline form per student without a user_id; "Login active" shown once one exists). Verified end to end against a real running dev server -- signed up a parent, added a student, created that student's login through the actual request the UI makes, then signed in AS that student account via better-auth's real sign-in and confirmed role='student' and the correct household_id came back -- plus new integration tests (student-login.integration.test.ts: creation works via a real sign-in, double-login rejected, duplicate email rejected) and a new cross-household case added to the T02 sweep (another household's parent gets 404 creating a login for a student she doesn't own). This closes only the creation gap -- F010's actual AC (a toggle to enable/disable an existing student's access, with a friendly locked screen when disabled) is still genuinely not built, so Status stays Not Started.
A14: M03 | B14: F011 | C14: Core schema migration v1 | D14: As a developer I want the schema versioned so that environments stay in sync. | E14: All 26 tables from tab 04 created via numbered migrations; up/down tested; migration runs in CI against a scratch DB. | F14: P0 | G14: L | H14: 5 | I14: S1 | J14: Done | K14: All 32 tables (tab04 lists 32, not 26) created via numbered Kysely migrations against a live Supabase dev project (examprep-ai-dev). Full up/down/up round-trip verified manually. CI workflow (.github/workflows/migrations.yml) verified green on GitHub Actions 2026-09-20 (migrate up, all the way down, back up against a scratch Postgres 17). DB choice: Supabase (Postgres 17), auth stays better-auth per CLAUDE.md — RLS is off pending M20.
A15: M03 | B15: F012 | C15: Seed & fixture data | D15: As a developer I want realistic seed data so that features can be built without manual entry. | E15: Seed loads 1 household, 2 students, 2 subjects, 15 chapters, 60 concepts, 200 questions, 3 historical evaluations. | F15: P0 | G15: M | H15: 2 | I15: S2 | J15: Done | K15: seed.ts now writes exactly the AC's numbers: 15 chapters (2 original + 13 new topic chapters), 60 concepts, 200 questions (all bulk-approved -- short_answer isn't an objective type so F117's tier logic would otherwise leave it in draft with no review-queue UI to approve it from), 2 subjects (MATH-SEED plus a deliberately small SCI-SEED stub -- CLAUDE.md's launch scope is Class 7 Maths only, so the second subject exists to prove multi-subject routes work, not to carry curriculum depth), 1 household with 2 students, and 3 confirmed historical evaluations (40%/80%/60%, via real generatePaper -> attempt -> answer -> submit -> createEvaluation -> confirmEvaluation calls, not hand-inserted rows). All new volume lives under brand-new chapters (chapter_no 3-15) rather than the original chapter 1/2 -- four existing integration test files generate real papers scoped to 'chapter_no=1 of MATH-SEED' and depend on it having exactly their own fixture questions as eligible candidates; adding more approved questions there would have made those tests' random picks nondeterministic. seed.ts also gained an entry-point guard (only auto-runs main() when invoked directly, via pathToFileURL against process.argv[1] -- the Windows-safe pattern already used by the migration runner) so seedBulkFixtures can be called standalone against a DB that already has MATH-SEED, which is exactly how this was verified: run once against the real dev DB, counts confirmed by direct query (15/60/200/2/3), then the full test suite re-run clean (89 tests) to prove the isolation actually holds.
... A20: M04 | B20: F017 | C20: Textbook source registry | D20: As a coach I want each chapter tied to a specific textbook so that NCERT vs Oxford scope differences are respected. | E20: Source record: publisher, title, edition, chapter no, page range, PDF reference; two sources may cover the same topic with different scope. | F20: P0 | G20: M | H20: 2 | I20: S3 | J20: Done | K20: sources table + repository already existed from F011/F013; no additional route needed beyond what chapters already expose (source_id, and chapter creation happens via the skill/seed path per F015's resolution, not a REST endpoint).
A21: M04 | B21: F018 | C21: Concept prerequisite graph | D21: As a system I want concept prerequisites so that remediation can go one level down. | E21: Concept can list prerequisite concept IDs; weak concept surfaces its unmastered prerequisites in the diagnosis. | F21: P2 | G21: M | H21: 3 | I21: S8 | J21: Done
A22: M04 | B22: F019 | C22: Syllabus import from PDF (assisted) | D22: As an admin I want to paste a chapter PDF and get a draft scope so that setup is fast. | E22: Upload chapter PDF, AI proposes concept list + IN/OUT scope, admin edits and approves; nothing saves without approval. | F22: P2 | G22: L | H22: 4 | I22: S10 | J22: Not Started
A23: M05 | B23: F020 | C23: Question CRUD with full metadata | D23: As an admin I want to author questions with all tags so that papers can be assembled by rule. | E23: Fields: concept, bloom, difficulty, marks, type, text, options, answer, hint, step-marks, tags, diagram, language, source; validation per type. | F23: P0 | G23: L | H23: 4 | I23: S3 | J23: Done | K23: POST/GET /api/questions, PATCH /api/questions/:id (admin-only). Question+options+step_marks written as one transaction (src/lib/questions.ts). Type-specific validation via Zod: mcq requires exactly one correct option. Verified live end to end.
A24: M05 | B24: F021 | C24: Step-mark / marking scheme storage | D24: As an evaluator I want stored step marks so that partial credit is consistent. | E24: Marks broken into named steps (e.g. Formula 1, Substitution 1, Answer+unit 1) summing to question marks; enforced by validation. | F24: P0 | G24: M | H24: 3 | I24: S4 | J24: Done | K24: Step marks stored in question_step_marks (F011/F013); creation validates sum(step_marks.marks) === question.marks server-side, verified live (mismatched sum -> 400 with the actual vs expected numbers in the message).
A25: M05 | B25: F022 | C25: Bulk import (CSV / JSON) | D25: As an admin I want to import a question set so that seeding is not manual. | E25: CSV/JSON import with row-level validation report; partial import allowed; rejected rows downloadable with reasons. | F25: P1 | G25: M | H25: 2 | I25: S4 | J25: Done | K25: POST /api/questions/bulk-import (tab05's exact route, Admin, multipart file field, format inferred from the filename extension unless overridden). Extracted the single-question validation (previously inline in POST /api/questions) into a shared questionInputSchema (src/lib/questions.ts) so one question is never valid by different rules depending on which route it came through. Each row -- CSV via papaparse, JSON via a plain array -- is validated and inserted independently through the same schema + createQuestion(), so one bad row never blocks the rest ('partial import allowed'); the JSON response's per-row {row, status, question_id | errors} is the 'rejected rows with reasons' report itself, not a separate download artifact. CSV supports the common case only -- mcq/fill_blank/short_answer with up to 4 lettered options via option_a_text/option_a_correct-style columns -- since CSV can't naturally represent step_marks or open-ended option counts; JSON is the richer path for those. Verified live against the real dev DB: a 2-row CSV (1 valid mcq, 1 missing its answer) imports the valid row and reports the invalid one with a concept-specific error message, a JSON import does the same, and admin-only access is enforced. Full suite green (102 tests).
A26: M05 | B26: F023 | C26: Duplicate & near-duplicate detection | D26: As an admin I want duplicates flagged so that a paper never repeats a question. | E26: Exact-hash plus embedding similarity check on save; >0.9 similarity warns with a link to the existing question. | F26: P1 | G26: M | H26: 3 | I26: S5 | J26: In Progress | K26: Exact-hash half only -- the embedding-similarity half of the AC needs an AI embeddings provider, and no ANTHROPIC_API_KEY (or any provider) is configured. Migration 0042 adds questions.text_hash (sha256 of lowercased, whitespace-collapsed text), backfilled in JS using the exact same computeTextHash() new inserts use (not a separately-written SQL equivalent, which risks silently diverging from the real algorithm), indexed per concept. createQuestion() now looks up an existing, non-retired question in the same concept with the same hash before inserting, and returns duplicate_of:{id,text} rather than blocking the save -- 'warns with a link to the existing question', not a hard stop. Wired through both POST /api/questions and F022's bulk import (each row's result). Scoped per-concept, not global: the same worked example can legitimately appear under two different concepts. Verified live against the real dev DB: an exact match (including a case/whitespace variant) in the same concept is flagged, the same text under a different concept is not, and a genuinely new question isn't flagged. Also cleaned up orphaned rows left behind by an unrelated Vitest worker crash during this same session (a one-off infra fluke, confirmed non-reproducible across two clean re-runs) -- unrelated to this feature but caught while verifying it. Full suite green (105 tests). Marked In Progress: the similarity-based near-duplicate half of the AC isn't built.
A27: M05 | B27: F024 | C27: Diagram & figure support | D27: As an author I want diagram questions so that geometry and biology are testable. | E27: Diagram type + parameters render as SVG (intersecting lines, transversal, number line, place-value, circuit, ray diagram); prints cleanly. | F27: P1 | G27: L | H27: 4 | I27: S5 | J27: Done
A28: M05 | B28: F025 | C28: AI question generation with review queue | D28: As an admin I want AI to draft questions so that the bank grows quickly. | E28: Generate N questions for a concept at a given Bloom/difficulty; output lands in review queue as Draft; only approved questions enter papers. | F28: P1 | G28: L | H28: 4 | I28: S6 | J28: Done | K28: New POST /api/questions/generate (tab05's exact route) implements AI-01: takes concept_id/count/bloom/difficulty, loads the concept plus its chapter's chapter_scope (IN/OUT), and prompts a strong model with the concept's idea/rule/example, the real IN-scope item list, the real OUT-scope list, and up to 3 approved same-concept/bloom/difficulty exemplars for style. Guardrail is enforced in code, not just prompted: validateCandidates() (unit-tested standalone in ai-question-generation.test.ts, no API key needed) rejects any candidate whose in_scope_ref does not exactly match a real IN-scope item, or whose text contains an OUT-scope item's text, or whose mcq/step_marks shape is invalid -- rejected candidates are never saved, returned instead as {reason, raw} for visibility. Migration 0044 adds questions.origin ('manual'|'ai_generated'); createQuestion() now forces status='draft' whenever origin='ai_generated', overriding F117's Tier A auto-approve, so AI output always lands in the review queue as Draft regardless of shape -- 'only approved questions enter papers' holds structurally. 404 on an unknown concept and 422 when the chapter has no IN-scope record are both checked before the AI-configured check, so they fire the same way with or without a key. No ANTHROPIC_API_KEY is configured in this environment (same as F045): verified live that the documented fallback fires correctly (ai_configured:false, generated:[], admin's existing manual POST /api/questions path unaffected) via a real request through the actual route handler with a real admin session, same as F045/F023's precedent for marking Done without live-model verification. Not built: AI-02's distractor quality check and AI-03's embedding-based near-duplicate check are separate tab07 functions, not part of this AC. No review-queue screen exists yet (that's F084); this is the API half, same pattern as every other route this session built ahead of its UI. Full suite green (139 tests, up from 129), tsc/eslint clean. [2026-09-17 UPDATE] The Draft-then-review behaviour for AI-generated output was removed along with F117/F084 (migration 0061_remove_question_approval_workflow) -- createQuestion() no longer forces status='draft' for origin='ai_generated'; every generated question is approved and immediately eligible for papers. 'Only approved questions enter papers' still holds (trivially, since nothing is ever anything else), but there is no longer a human review step between generation and use.
A29: M05 | B29: F026 | C29: Question usage history | D29: As a system I want to know when a question was last served so that recent repeats are avoided. | E29: Per student, last_served_at and times_served; generator excludes questions served within a configurable window. | F29: P1 | G29: S | H29: 1 | I29: S6 | J29: Done | K29: The exclusion mechanic already existed (generatePaper's recentUsageWindowDays, default 14 days) but was only reachable by calling generatePaper() directly -- every test in this repo does that, but the real POST /api/papers/generate route never exposed it, so 'configurable window' wasn't actually true for a real caller. Added recent_usage_window_days to the route's schema (nonnegative int, passed through as-is). Added questionUsageRepository.summaryForStudent() (last_served_at via MAX(served_at), times_served via COUNT, grouped per question) and wired it into GET /api/questions via an opt-in student_id query param -- usage is meaningless without a specific student to ask about, so it's additive/opt-in rather than always joined. Verified live against the real dev DB with a fixture sized to make the window's effect directly observable (exactly one eligible question): first generation uses it, a second generation with the default window hits a shortfall (correctly excluded), and recent_usage_window_days:0 makes it eligible again through the real route -- then GET /api/questions?student_id=... reports times_served:2. Full suite green (109 tests).
A30: M06 | B30: F027 | C30: Blueprint definition engine | D30: As a coach I want the school's real paper pattern stored so that mocks match the exam. | E30: Blueprint: sections with name, question count, marks each, type mix, Bloom mix, choice rules, word limits; a blueprint is data, not code. | F30: P0 | G30: L | H30: 5 | I30: S6 | J30: Done | K30: GET/POST /api/blueprints (admin-only POST), sections/bloom_targets/choice_rules as jsonb. total_marks is server-derived from sections, not client-supplied. choice_rules is accepted and stored but not used by the generator (F030 deferred). Verified live: non-admin POST -> 403, admin POST -> 201 with correct derived total_marks. The /generate screen (built after this ticket) now drives this via a real UI -- student/blueprint/chapter pickers, shortfalls rendered to the parent, browser-verified end to end against a live dev server (a fresh sign-up, add a student, generate a paper, confirm the shortfall list renders when the seed question bank can't fill a slot).
A31: M06 | B31: F028 | C31: Weighted concept selection (40/40/20) | D31: As a coach I want papers to over-test weak concepts so that practice is targeted. | E31: Selection draws 40% from WEAK/PRIORITY, 40% NEEDS PRACTICE, 20% STRONG per the tracker; actual distribution is shown to the parent. | F31: P0 | G31: L | H31: 4 | I31: S6 | J31: Done | K31: src/lib/papers.ts generatePaper() buckets concepts into weak+priority / needs-practice / strong per the student's concept_status (no-status concepts default to needs-practice) and apportions each section's slots 40/40/20 via largest-remainder rounding so counts always sum exactly. Actual achieved bucket mix is written to papers.weighting.actual. Verified live end to end with a real weak/neutral/strong concept fixture -- correct per-bucket question counts, including a supply-constrained run that exercised partial fulfilment correctly. The /generate screen (built after this ticket) now drives this via a real UI -- student/blueprint/chapter pickers, shortfalls rendered to the parent, browser-verified end to end against a live dev server (a fresh sign-up, add a student, generate a paper, confirm the shortfall list renders when the seed question bank can't fill a slot).
A32: M06 | B32: F029 | C32: Bloom & difficulty balancing | D32: As a coach I want the cognitive mix honoured so that papers are not all recall. | E32: Generator satisfies the blueprint's Bloom targets within +/-5 percentage points, or reports why it could not. | F32: P0 | G32: M | H32: 3 | I32: S7 | J32: Done | K32: Actual Bloom mix is computed post-selection and compared to blueprint.bloom_targets; any Bloom level off by more than 5 percentage points is appended to papers.shortfalls with the actual vs target numbers, verified live in the supply-constrained test run (correctly flagged both a 12pp Remember and 12pp Understand deviation once shortfalls skewed the mix). The /generate screen (built after this ticket) now drives this via a real UI -- student/blueprint/chapter pickers, shortfalls rendered to the parent, browser-verified end to end against a live dev server (a fresh sign-up, add a student, generate a paper, confirm the shortfall list renders when the seed question bank can't fill a slot).
A33: M06 | B33: F030 | C33: Internal choice (OR) handling | D33: As a student I want internal choice so that the paper matches the board pattern. | E33: Choice pairs marked in the paper, counted once in total marks, and handled correctly in evaluation and coverage stats. | F33: P1 | G33: M | H33: 2 | I33: S7 | J33: Done
A34: M06 | B34: F031 | C34: Manual paper builder | D34: As a coach I want to swap a question so that I retain final control. | E34: Drag/replace a selected question; regenerate a single slot; lock questions before regenerating the rest. | F34: P1 | G34: M | H34: 3 | I34: S7 | J34: Done | K34: POST /api/papers/:id/regenerate-slot swaps one slot in place (same concept/bloom/marks as the slot being replaced, excluding every question already used in that paper) without touching any other paper_questions row -- 'lock others' is inherent since only the named slot is ever updated. Verified live: regenerated a slot to a different question of the same shape, and confirmed cross-household denial (404). Drag-and-drop UI obviously doesn't exist -- no screens exist in this repo at all -- this is the API half only.
A35: M06 | B35: F032 | C35: Coverage guard & shortfall reporting | D35: As a coach I want to know when the bank cannot fill a blueprint so that I am not given a silently weak paper. | E35: If a slot cannot be filled, the paper is still produced with an explicit shortfall note naming the concept and slot. | F35: P0 | G35: S | H35: 2 | I35: S7 | J35: Done | K35: Unfillable slots do not block generation -- the paper is produced with a shortfalls entry naming the exact section, bucket, and constraint (bloom/difficulty/marks) that had no eligible approved question. Verified live: a deliberately undersupplied fixture (1 eligible question per bucket where 2 were needed) generated a 6-question paper instead of erroring, with 2 shortfall entries pinpointing exactly which slots came up short. The /generate screen (built after this ticket) now drives this via a real UI -- student/blueprint/chapter pickers, shortfalls rendered to the parent, browser-verified end to end against a live dev server (a fresh sign-up, add a student, generate a paper, confirm the shortfall list renders when the seed question bank can't fill a slot).
A36: M07 | B36: F033 | C36: Print-exact A4 PDF renderer | D36: As a parent I want a printable paper so that my child writes it like a real exam. | E36: Server-side HTML to PDF, A4, correct margins, page breaks never split a question, printBackground on, embedded fonts. | F36: P0 | G36: L | H36: 5 | I36: S8 | J36: Done | K36: GET /api/papers/:id/pdf (tab05's exact contract: Parent role, theme + include_key query params, application/pdf stream) renders the paper via Playwright/headless Chromium (tab09's locked choice, now actually installed -- playwright + a downloaded Chromium build). A4 via page.pdf()'s margin option, printBackground:true, page-break-inside:avoid on every question block so a question is never split across a page. Embedded fonts happen automatically -- Chromium's PDF export always subsets and embeds whatever font the page actually renders with (Georgia here). theme is accepted per the contract but not yet acted on since no theme packs exist (F034/F120 Not Started) -- every request renders the one 'Plain' layout. Verified live: generated a real PDF against the real dev DB (src/routes/papers-pdf.integration.test.ts), confirmed the %PDF- magic header, a realistic byte size, and (via a manual screenshot render, not committed) that the layout actually looks like an exam paper -- header, sectioned questions, numbered continuously across sections, marks in brackets.
A37: M07 | B37: F034 | C37: Paper theme templates | D37: As a student I want an appealing paper so that practice feels less dull. | E37: At least two themes (plain school format, illustrated/comic format) selectable at generation; both print in black-and-white legibly. | F37: P1 | G37: M | H37: 3 | I37: S8 | J37: Done
A38: M07 | B38: F035 | C38: Rough-work column & answer space | D38: As a coach I want a printed rough-work column so that working is separated from the answer. | E38: Every working page carries a narrow ruled rough column, ruled answer panels sized to the marks, and a labelled draw-here box for diagrams. | F38: P0 | G38: M | H38: 2 | I38: S8 | J38: Done | K38: Built into the same paper-template.ts used by F033's route: a 16mm ruled rough-work column pinned with position:fixed so it repeats on every printed page (Chromium's standard trick, since @page margin boxes aren't supported), ruled answer-line panels sized to the question's marks (short_answer/long_answer scale with marks; fill_blank gets one line; mcq/assertion_reason/match/multi_statement get an options list instead), and a labelled 'Draw here' box whenever a question's diagram_kind is set, regardless of its base type. Not print-QA'd on a real printer/multiple devices (F107 Not Started) -- verified only via a rendered PDF/screenshot in this dev environment.
A39: M07 | B39: F036 | C39: Answer key + marking scheme export | D39: As a parent I want the key separately so that I can mark without seeing it beforehand. | E39: Separate PDF: answers, step-wise marks, expected diagram description; never bundled into the student paper file. | F39: P0 | G39: M | H39: 2 | I39: S8 | J39: Done | K39: The same GET /api/papers/:id/pdf route (tab05 defines one route with an include_key boolean, not two separate paths) renders the answer key + step-wise marks + expected diagram description as a distinct trailing section (its own page-break-before, never interleaved with the paper's questions) when include_key=true -- and this branch is only ever reachable by the parent/admin-only route, so a student session can never produce or receive it, satisfying the hard rule structurally, not just by convention. Verified live: the include_key=true response is a strictly larger PDF with more pages than the default response (src/routes/papers-pdf.integration.test.ts), and a correct-option-letter test question round-trips through the key with the right label.
A40: M07 | B40: F037 | C40: Concept coverage & Bloom table | D40: As a coach I want the coverage table so that I can verify what the paper actually tested. | E40: Auto table: concept, questions, marks, % weight, Bloom split; appended to the key, also shown on screen. | F40: P0 | G40: S | H40: 2 | I40: S8 | J40: Done | K40: computeCoverageTable() (src/lib/pdf/coverage.ts) computes concept/questions/marks/%weight/Bloom-split per concept actually used on a paper. It's appended to the answer-key PDF (F036) and also served standalone as JSON at GET /api/papers/:id/coverage (tab05's exact route) -- the 'shown on screen' half of the AC has real data to call now, even though no screen exists anywhere in this repo (M14 dashboards are all Not Started). Verified live against the real dev DB with a 2-question, 2-Bloom-level fixture.
A41: M07 | B41: F038 | C41: Paper library & versioning | D41: As a parent I want past papers stored so that I can reprint or compare. | E41: Every generated paper persisted with its question IDs and blueprint version; re-download reproduces the identical PDF. | F41: P1 | G41: M | H41: 2 | I41: S9 | J41: Done | K41: "Every generated paper persisted with its question IDs" was already true (F011's schema: paper_questions rows are never touched once written, per the 'nothing is deleted' invariant). The real gap was 'blueprint version' -- papers stored only a live blueprint_id FK, so if a blueprint were ever edited in place, an old paper's notion of 'its blueprint' would silently mean whatever the blueprint looks like today. Migration 0041 adds papers.blueprint_version, backfilled from each existing paper's current blueprint.version (defaults to 1 for any future direct insert that doesn't specify one, matching blueprints.version's own default), and generatePaper() now snapshots it at generation time. No blueprint edit route exists yet (tab05 only lists POST /api/blueprints, no PATCH), so this was a forward-looking fix, not an active bug. 'Re-download reproduces the identical PDF' verified live via GET /api/papers/:id/pdf called twice against the real dev DB: identical page count and near-identical byte size -- not byte-for-byte identical, since Chromium stamps a fresh /CreationDate into every PDF export with no Playwright option to override it, so 'identical' here means identical rendered content, not an exact byte match. Full suite green (97 tests).
A42: M08 | B42: F039 | C42: Timed attempt runner | D42: As a student I want a timer so that I practise exam pacing. | E42: Countdown per paper duration, visible section navigator, warning at 10 minutes, auto-submit at zero with all saved answers. | F42: P0 | G42: L | H42: 4 | I42: S9 | J42: Done | K42: Server side only: POST /api/attempts records a server-side started_at, and POST /api/attempts/:id/submit computes duration_used_sec from it -- this is the honest server half of the AC. Countdown UI, visible section navigator, 10-minute warning, and genuine auto-submit-at-zero all need a client timer or a background job; none exist. No screens exist anywhere in this repo, and no background-job infra is installed (tab09 names Inngest/Trigger.dev, neither chosen). The screen now exists (src/routes/attempt/$id.tsx): a client-side countdown computed from paper.duration_min and attempt.started_at (server truth, so it survives refresh) and section navigation as jump links grouped by paper_questions.section. Still missing the AC's 10-minute warning and genuine auto-submit-at-zero -- the client only swaps the clock's text to "Time's up" once remaining time hits zero and never calls submit itself; no background job exists to enforce this server-side either, so the attempt just sits open past the deadline until the student submits by hand. Verified live end to end as part of the same run described under F040's note.
A43: M08 | B43: F040 | C43: Autosave & resume | D43: As a student I want my answers saved so that a lost connection does not lose my work. | E43: Answer saved within 2s of change and on blur; refresh or device change resumes at the same question with the timer intact. | F43: P0 | G43: M | H43: 3 | I43: S9 | J43: Done | K43: PATCH /api/attempts/:id/answer is the autosave endpoint itself -- one upsert per call on the (attempt_id, paper_question_id) unique constraint from F011, verified live. The "within 2s" debounce and "resume at the same question" are client behaviour; the server makes resume possible (GET /api/papers/:id + the saved attempt_answers already give a client everything needed to restore state) but no client exists to do it. A client now exists (src/routes/attempt/$id.tsx): each answer edit is saved via a 600ms debounce calling this same PATCH /answer endpoint -- not literally "within 2s of change and on blur" since there is no separate blur handler, just the debounce, but comfortably under the 2s bar. Resume is real for answers: a new GET /api/attempts/:id endpoint (src/routes/api/attempts/$id.ts) returns the attempt, paper header, and every question with any previously-saved answer, and the screen pre-fills its state from that on load -- verified live (saved an answer, re-fetched, got it back). "Resumes at the same question" doesn't strictly apply to this screen's layout, since every question renders on one page with section jump links rather than one question at a time, so there is no single "current question" position to restore; the timer stays intact across reload because it is recomputed from the server's started_at rather than kept client-side. This GET endpoint deliberately builds its own narrow response projection instead of reusing paperQuestionsRepository.listForPaperWithQuestions / questionOptionsRepository.listByQuestion directly, because those select questions.answer and is_correct for grading elsewhere -- this is the one place in the product where the "student can never see an answer key" rule (T09) is load-bearing at the wire level, and it has its own dedicated integration tests (src/routes/attempt-detail.integration.test.ts, 4 tests covering the missing answer key, is_correct flags, resume state, and cross-student 404) plus a cross-household case added to the T02 sweep (src/routes/cross-household-access.integration.test.ts).
A44: M08 | B44: F041 | C44: Per-question time capture | D44: As a coach I want time per question so that pacing problems are visible. | E44: Seconds spent per question recorded; report flags questions consuming >2x their mark-proportional time budget. | F44: P1 | G44: M | H44: 2 | I44: S10 | J44: Done | K44: time_spent_sec is accepted and stored per answer via PATCH /api/attempts/:id/answer (verified live). The pacing-anomaly report ('flags questions consuming >2x their mark-proportional time budget') is not built -- that is an analysis/reporting endpoint over this data, not storage, and no such route is listed in tab05. The new /attempt/:id screen (src/routes/attempt/$id.tsx) does not send time_spent_sec on any answer save -- its autosave call only ever posts paper_question_id plus selected_option/response_text, so this field is still never populated by a real client despite the storage and endpoint support already existing. No progress on the pacing-anomaly report either.
A45: M08 | B45: F042 | C45: Answer input types | D45: As a student I want the right input per question type so that answering is natural. | E45: MCQ radio, fill-in text, true/false, short answer textarea, long answer rich text; math input helper for symbols and fractions. | F45: P0 | G45: M | H45: 3 | I45: S9 | J45: Done | K45: Schema already carries whatever shape each type needs (attempt_answers.response_text / selected_option); the PATCH /answer endpoint accepts both generically and does not care which input widget produced them. Radio/textarea/rich-text/math-symbol widgets are UI components -- not applicable without screens. The screen now exists (src/routes/attempt/$id.tsx) but only implements two of the five listed widgets: real MCQ radio buttons rendered from the question's actual options, and a single generic textarea used for every non-mcq type alike -- fill-in, true/false, short answer, and long answer all get the same plain textarea, with no true/false-specific control, no rich text editor for long answers, and no math input helper for symbols or fractions. AC still only partially met.
A46: M08 | B46: F043 | C46: Review-before-submit screen | D46: As a student I want to see blanks before submitting so that I stop leaving questions empty. | E46: Grid of answered/unanswered/flagged; explicit 'you have N blank answers' warning implementing the Never Blank habit. | F46: P0 | G46: S | H46: 2 | I46: S10 | J46: Done | K46: The blank-answer block is real and server-enforced, not just a UI nag (T11): POST /api/attempts/:id/submit computes which paper_questions have no non-empty answer and returns 409 with the exact blank question positions unless the client resubmits with confirm_blanks:true. Verified live: submitting with 1 of 3 blank -> 409 naming position 3; resubmitting with the override -> closes the attempt. The review grid itself (answered/unanswered/flagged visual) is UI, not built. The review grid now exists (src/routes/attempt/$id.tsx, review mode): every question renders as a numbered cell colored for blank/flagged/answered, with an explicit "N question(s) are still blank" (or "Every question has an answer") line above it, satisfying the AC's grid-plus-explicit-count wording. One nuance worth flagging: the screen computes blank/flagged state client-side to draw the grid and to decide what to send, then passes confirm_blanks pre-emptively based on that count rather than making a bare first submit call and reacting to a 409 -- so in the normal flow this screen's own submit never actually round-trips the 409 it describes above, it only would in a hypothetical race where local state is ahead of the last autosave. The 409 path itself is unchanged and still verified live (1 of 3 blank -> 409 naming position 3, resubmit with the override -> closes the attempt). Flagging is client-side only and does not persist across reload -- there is no flagged column anywhere in the schema (attempt_answers or otherwise), a disclosed gap rather than an oversight.
A47: M09 | B47: F044 | C47: Objective auto-scoring | D47: As a parent I want MCQs marked instantly so that I do not mark them by hand. | E47: MCQ, true/false, fill-in scored with answer normalisation (case, units, symbols, Indian/international numerals); accuracy validated on a 100-answer fixture. | F47: P0 | G47: M | H47: 3 | I47: S10 | J47: Done | K47: src/lib/scoring.ts scoreObjectiveAnswer(), matching tab07 AI-04 exactly ('deterministic code, no AI'). normalizeAnswer() strips case/commas/currency-percent-degree symbols/common unit words so Indian '1,00,000' and international '100,000' grouping compare equal. Verified live: a correct MCQ auto-scored full marks with zero AI involvement.
A48: M09 | B48: F045 | C48: AI-assisted subjective scoring | D48: As a parent I want long answers pre-marked so that evaluation takes minutes not hours. | E48: AI returns marks per step with justification against the stored marking scheme; never final until a human confirms. | F48: P0 | G48: L | H48: 5 | I48: S11 | J48: Done | K48: src/lib/ai-grading.ts gradeSubjectiveAnswer() implements AI-05 (Claude Sonnet, tab07's 'strong model' tier): proposes marks per step with justification, error_type, and feedback as JSON, written to ai_marks/ai_error_type -- never to marks_awarded/error_type directly, so nothing it produces counts until a human confirms (CLAUDE.md hard rule). Gracefully returns null with no ANTHROPIC_API_KEY configured (none is, in this dev environment), and the caller falls back to tab07's own documented fallback ('needs manual marking'), verified live. Real AI grading itself is UNTESTED end-to-end -- needs a real API key to exercise.
A49: M09 | B49: F046 | C49: Error classification | D49: As a coach I want each lost mark typed so that I know what to fix. | E49: Every non-full-mark answer gets one of: Conceptual Gap, Calculation Error, Presentation Issue, Formula/Definition Error, Incomplete, Not Attempted. | F49: P0 | G49: M | H49: 3 | I49: S11 | J49: Done | K49: The 6-category error_type is now a real CHECK constraint (migration 0038), not free text. Objective wrong answers default to Conceptual Gap (an objective question can't show *why* it was wrong without shown work); subjective error_type comes from AI-05's classification when available. Verified live end to end as part of the full evaluate flow.
... A56: M10 | B56: F053 | C56: Low-confidence flagging & confirm loop | D56: As a parent I want unclear text flagged so that the AI does not guess a mark. | E56: Any answer below the confidence threshold is shown side-by-side with the image crop and must be confirmed before scoring. | F56: P1 | G56: M | H56: 3 | I56: S13 | J56: Done | K56: Built 2026-09-30. Threshold 0.85 (OCR_CONFIDENCE_THRESHOLD). Each reading is shown under its crop of the photo; unclear ones must be confirmed or corrected; an MCQ option the question never printed drops to confidence 0. POST /api/attempts/:id/scan/apply re-checks everything server-side (409 needs_review). The parent or the student can confirm.
A57: M10 | B57: F054 | C57: Presentation habit detection from image | D57: As a coach I want habits observed from the scan so that H7-H10 are tracked objectively. | E57: Detects and logs: missing units, overwriting/scribbles, working outside the rough column, blank sub-parts; each stored as an observation, not a mark. | F57: P2 | G57: L | H57: 4 | I57: S14 | J57: Not Started
A58: M11 | B58: F055 | C58: Knowledge Score capture | D58: As a coach I want a second score so that I can separate knowing from delivering. | E58: For each lost-mark question the reviewer marks whether the concept was actually known; Knowledge Score computed alongside Actual Score. | F58: P0 | G58: M | H58: 3 | I58: S13 | J58: Done | K58: knowledge_known was already collectible per item via F047's PATCH endpoint (built in M09); this feature is the missing computation: Knowledge Score = actual_score plus every lost mark where the reviewer marked knowledge_known=true, computed in confirmEvaluation(). Verified live: two 1-mark items both scored 0, one marked knowledge_known=false (real gap) and one true (delivery issue) -> knowledge_score=1, crediting back exactly the delivery-issue mark.
A59: M11 | B59: F056 | C59: Delivery Gap computation & KPI | D59: As a coach I want the gap tracked so that it becomes the headline metric. | E59: Delivery Gap = Knowledge - Actual per paper, per subject and rolling; charted over time against a configurable target. | F59: P0 | G59: M | H59: 2 | I59: S13 | J59: Done | K59: delivery_gap = knowledge_score - actual_score, computed and stored at confirm time alongside percentage and a grade band. Verified live (delivery_gap=1 in the same test). 'Charted over time against a configurable target' is a tab06 dashboard/chart concern -- no screens exist in this repo, so only the underlying per-evaluation number is built, not the rollup or chart.
A60: M11 | B60: F057 | C60: Behaviour pattern library (P1-P6) | D60: As a coach I want named patterns so that the same problem is recognised across subjects. | E60: Patterns configurable, not hardcoded: One-Idea Stop, Blank Retreat, First-Plausible Commit, Label Flip, Rule Over-Extension, Format Miss; each answer can carry one or more. | F60: P0 | G60: L | H60: 4 | I60: S14 | J60: Done | K60: The 6 named patterns (One-Idea Stop, Blank Retreat, First-Plausible Commit, Label Flip, Rule Over-Extension, Format Miss) seeded as real, editable patterns rows (npm run db:seed:patterns, idempotent -- verified by running it twice) rather than hardcoded in code, matching the AC's 'configurable, not hardcoded'. Descriptions are working definitions inferred from the names (only First-Plausible Commit had an existing definition, in the question-generation skill) -- meant to be refined by the user, not treated as authoritative. Attaching patterns to an answer piggybacks on PATCH /api/evaluations/:id/items/:itemId via an optional pattern_ids field, since tab05 lists no dedicated route for it; verified live end to end including the report correctly aggregating pattern counts.
A61: M11 | B61: F058 | C61: Presentation habit tracker (H1-H10) | D61: As a coach I want habits scored per paper so that improvement is visible. | E61: Each habit rated present/partial/absent per paper with a trend line; habits are editable records, not code constants. | F61: P1 | G61: M | H61: 3 | I61: S14 | J61: Done | K61: Closed the one gap this row was left In Progress for: "no screen to show ratings on." GET /api/evaluations/:id now also returns the full H1-H10 habit library plus this evaluation's current ratings (same reasoning as F048/F057's pattern library addition), and /evaluate/:attemptId (src/routes/evaluate/$attemptId.tsx) renders a "Presentation habits" card: present/partial/absent radios per habit before confirming (Save habits PATCHes the existing .../habits endpoint), a read-only summary after. /home (src/routes/home.tsx) adds a "Presentation habits" card reading the existing trend endpoint, rendering each habit's full rating history as a row of small colored, letter-labelled dots (P/~/A, oldest to newest) plus a "latest: X" text line -- color is a secondary cue per the dataviz skill (STATUS palette: present=good, partial=warning, absent=critical), never the only signal, since every dot also carries its own letter. New integration test assertion (habits.integration.test.ts) proves GET /api/evaluations/:id returns all 10 habits with the two already-rated ones showing their saved rating and the rest null. e2e/happy-path.spec.ts extended to rate a habit through the real UI, save it, confirm, and verify it shows up in the /home trend -- this surfaced and fixed a real test mistake (not a product bug): CardTitle renders a styled <div>, not a semantic heading, so getByRole('heading', ...) silently never matches card titles anywhere in this app -- fixed to a text match, matching how the rest of this suite already asserts on CardTitle content elsewhere. Also found and fixed the same pre-existing cross-test-contamination bug class as F048's remediation.integration.test.ts fix, this time in habits.integration.test.ts (questions deleted by a shared created_by literal instead of this run's own question id). Full suite green (186 tests, up from 184), all 3 E2E specs passing.
A62: M11 | B62: F059 | C62: Paper diagnosis report | D62: As a parent I want one page that explains the score so that I know what to do next. | E62: Report: score, grade, Delivery Gap, error inventory table, pattern hits, habit status, three ranked actions, one parent action. | F62: P0 | G62: L | H62: 4 | I62: S14 | J62: Done | K62: GET /api/evaluations/:id/report, rule-based end to end (src/lib/diagnosis.ts) -- deliberately built as AI-10's own documented fallback ('rule-based template report') rather than a live AI call, since AI-10's guardrail already says 'the model never computes scores' regardless. Returns score/grade/gap, an error inventory (lost-mark questions only, with any attached pattern hits), aggregated pattern counts, and up to 3 ranked actions drawn from the student's Weak/Priority concepts tracker-wide (not just this paper) plus a single parent action. habit_status is an empty array (F058 not built). Verified live against the full report shape.
A63: M11 | B63: F060 | C63: Careless-vs-concept separator | D63: As a coach I want reading errors distinguished from gaps so that the fix is right. | E63: Reversal-word questions (NOT/least/false) tagged; wrong answers on them classified as reading discipline, routed to a drill instead of re-teaching. | F63: P1 | G63: M | H63: 2 | I63: S15 | J63: Done | K63: Closed both gaps this row was left In Progress for. (1) UI for tagging is_reversal_word: previously API/CSV-only -- added is_reversal_word to PATCH /api/questions/:id's schema and a checkbox in the admin review-queue expand view (src/routes/admin/questions.tsx), the only editable surface that exists for a question already in the bank. (2) "routed to a drill instead of re-teaching" now genuinely happens, not just as feedback text: buildRemediationPack (src/lib/remediation.ts) checks whether a student's confirmed wrong answers on the Priority concept were dominated by Reading Discipline error_type (new evaluationItemsRepository.countErrorTypesForConcept) -- if so it skips the AI/bank refresher and worked examples entirely (nothing to re-teach), substitutes a fixed reading-discipline framing message, and biases question selection toward is_reversal_word-tagged questions (findRandomApprovedObjective gained a preferReversalWord order-by, not a filter, so a concept with too few tagged questions still fills the drill). The distinction is persisted via trigger_reason (no migration needed) and surfaced on /remediation: a "careful-reading practice" badge on the task list and "Why this drill" instead of "Refresher" as the card title. "Mostly reading discipline" is a strict-majority-of-error-types comparison -- not a stated threshold from the plan (none exists), same kind of documented default F118/F063 already use. New integration test (a second describe block in remediation.integration.test.ts) escalates a concept to Priority via two wrong answers on reversal-word-tagged questions and asserts drill_kind, the framing message, and that the reversal-word question is actually selected; the original describe block's existing test also now asserts drill_kind='concept_refresher' for its plain-question escalation, confirming no regression to the existing path. Full suite green (185 tests, up from 184), all 3 E2E specs still passing.
A64: M12 | B64: F061 | C64: Concept mastery ledger | D64: As a system I want every attempt logged per concept so that trends are real. | E64: Append-only attempt rows (date, marks, max, source paper); mastery % derived, never overwritten. | F64: P0 | G64: M | H64: 3 | I64: S10 | J64: Done | K64: concept_mastery ledger (F011/F013) + src/lib/mastery.ts recordMasteryAttempt(), which is a service function, not a route -- nothing in the app can call it yet since it is meant to run when an evaluation is confirmed (POST /api/evaluations/:id/confirm, M09), which does not exist. Verified via a fixture chain (blueprint->paper->attempt->evaluation created directly through existing repositories) that the ledger writes correctly and ratios/dates are recorded as append-only rows.
A65: M12 | B65: F062 | C65: Status & trend engine | D65: As a parent I want to see improving or declining concepts so that I can react. | E65: Status thresholds (Strong >=80, Needs Practice 50-79, Weak <50) and arrows from the last three attempts; thresholds configurable. | F65: P0 | G65: M | H65: 3 | I65: S10 | J65: Done | K65: Status thresholds (Strong>=80/Needs Practice 50-79/Weak<50) and trend (vs average of last 2 prior ratios) implemented in src/lib/mastery.ts, verified live through a 4-attempt sequence. Thresholds are named constants in one place ("configurable" in the sense of easy to change; not exposed as an admin-editable setting since no admin UI exists).
A66: M12 | B66: F063 | C66: Priority flag rules | D66: As a coach I want automatic escalation so that repeated weakness is never missed. | E66: Weak on 2nd appearance becomes PRIORITY and auto-triggers a 5-question mini test; >=85% twice moves to Maintenance; retire only after three. | F66: P0 | G66: M | H66: 3 | I66: S11 | J66: Done | K66: Weak-twice->Priority and >=85%-twice->Maintenance both verified live end to end, including the bug caught during testing where Priority was incorrectly clearing after a single good score (fixed: Priority now persists as the stored status until the explicit two-in-a-row recovery, not just checked against the last ledger row's label). "Retire only after three" does not map onto a schema value -- concept_status.status is a fixed 5-value CHECK with no Retired option, not added this pass. The auto-triggered 5-question mini test is not built -- needs the paper generator (M06).
A67: M12 | B67: F064 | C67: Cumulative tracker view | D67: As a parent I want one screen per subject so that I can see the whole picture. | E67: Sortable table by concept with attempts, latest, trend, status, last tested date; filter by status; export to CSV/PDF. | F67: P0 | G67: M | H67: 3 | I67: S12 | J67: Done | K67: GET /api/tracker/:studentId (only M12 route tab05 lists), household-scoped like every other student-facing route, with subject_id/status filters -- verified live including the cross-household 404. Sortable table view, CSV/PDF export, and the screen itself are tab06 UI work; no screens exist anywhere in this repo yet, consistent with everything built so far being API-only. [UPDATE] The screen itself (/tracker/:studentId) is now built -- sortable table (click any column header), status filter, trend arrows, and CSV export (client-side blob download of the currently filtered/sorted rows; PDF export still not built, no PDF renderer wired to this data). Backend gained two fields it never returned before: subject_name and last_tested_date (src/db/repositories/tracking.ts, joined from the append-only concept_mastery ledger via MAX(date), cast to text in SQL rather than left as a parsed JS Date -- pg parses DATE columns using the server process local timezone, which silently shifted the calendar day by one on round-trip). Linked from /home via a new persistent "Concept tracker" link. New tracker.integration.test.ts covers both fields plus the status filter. Discovered while answering a parent's "where do I see concept-wise strengths and weaknesses" question.
A68: M12 | B68: F065 | C68: Cross-subject weakness roll-up | D68: As a coach I want patterns that span subjects so that behaviour issues surface. | E68: Dashboard shows patterns and habits aggregated across all subjects, not just per paper. | F68: P1 | G68: M | H68: 2 | I68: S15 | J68: Done
A69: M13 | B69: F066 | C69: Auto-generated remediation pack | D69: As a student I want a drill when I fail a concept so that I fix it immediately. | E69: On PRIORITY flag the system builds: 2-3 line refresher, 2 solved examples, 3 practice questions with hidden answers; delivered in-app and as PDF. | F69: P1 | G69: L | H69: 4 | I69: S15 | J69: Done | K69: POST /api/remediation/generate (tab05's exact route): refuses to build a pack unless concept_status for that (student, concept) is currently 'Priority' -- the AC's literal trigger condition, checked server-side rather than trusted from the caller. Builds refresher + 2 examples (F067, cached per concept) + 3 practice questions (F068, drawn live, restricted to objective types) and writes one remediation_tasks row. Delivered in-app via GET /api/remediation and the new /remediation screen; PDF delivery (the AC's other stated channel) is not built -- F033's PDF pipeline exists for exam papers but was not wired to remediation packs in this pass, a stated gap. Shortfalls are reported (shortfall:true), never hidden, when fewer than 3 objective approved questions exist for the concept, per CLAUDE.md's hard rule. Verified live end to end against the real dev server and dev DB with Playwright, not just the API: escalated a real concept to Priority via two wrong exam rounds, generated a pack, and confirmed the screen renders it correctly. Full suite green (166 tests).
A70: M13 | B70: F067 | C70: Solved-example generation | D70: As a student I want worked steps so that I can copy the correct method. | E70: AI produces step-by-step solutions matching the stored marking scheme format; reviewed once per concept then cached, not regenerated per student. | F70: P1 | G70: M | H70: 3 | I70: S15 | J70: Done | K70: New concept_remediation_content table (migration 0046), one row per concept, exactly matching the AC: 'reviewed once per concept then cached, not regenerated per student.' First remediation request for a concept calls AI-09 (src/lib/ai-remediation.ts, same strong-model tier as AI-01/AI-05) for a refresher + 2 worked examples; every later request for that concept (any student) reads the cached row instead of calling the model again. No ANTHROPIC_API_KEY is configured in this environment (same as F025/F045): verified live that the documented fallback ('serve existing bank questions with no narrative', tab07) fires correctly -- source='bank_fallback', refresher=null, examples=[] -- through the real route with a real admin session. 'Reviewed once' review-gate UI does not exist (no admin screen approves cached content before it reaches a student) -- a stated gap, consistent with this session's pattern of shipping the mechanism with an honest review-workflow caveat (same shape as F025's Draft-always AI questions with no review-queue screen yet).
A71: M13 | B71: F068 | C71: Drill attempt & instant evaluation | D71: As a student I want my drill marked at once so that the loop closes. | E71: Drill attempt scored immediately; result writes back to the concept ledger and can clear or sustain the PRIORITY flag. | F71: P1 | G71: M | H71: 3 | I71: S16 | J71: Done | K71: New submitDrillAttempt() (src/lib/remediation.ts) builds a real papers/paper_questions/attempt chain for the task's 3 questions, then calls the exact same createEvaluation/confirmEvaluation functions M09 already built and tested -- 'writes back to the concept ledger' and 'clears or sustains PRIORITY' both fall out of F063's existing determineNextStatus state machine rather than new logic here. A drill auto-confirms in the same request with no parent-review gate between submit and confirm -- a deliberate, documented departure from the exam-paper flow, justified because every drill question is restricted to objective types (deterministic code-scored, never AI judgment) and this is low-stakes self-practice, not the graded record a parent reviews; CLAUDE.md's 'AI never finalises a mark' hard rule targets AI judgment calls, which are never in play here. New POST /api/remediation/:id/attempt (student-only, self-scoped, no id lets a student reach another's drill); a completed task 409s on resubmission. Found and fixed a real latent bug while building this: concept_mastery.date is a plain DATE column, so an exam evaluation and a same-day drill (exactly what remediation produces) couldn't be recency-ordered by date alone -- F063's 'two consecutive >=85% attempts' escalation rule reads 'most recent' via an ORDER BY date DESC LIMIT 2 with no tiebreaker, which could silently pick the wrong row. Migration 0047 adds concept_mastery.created_at as the real tiebreaker. Verified live end to end (real dev server + dev DB + Playwright): escalated a concept to Priority, then proved BOTH outcomes with real drill submissions -- one high-scoring drill sustains Priority (sticky), a second clears it to Maintenance -- confirmed via the actual concept_status row after each. Full suite green (166 tests, up from 158).
A72: M13 | B72: F069 | C72: Spaced re-test scheduling | D72: As a coach I want concepts re-tested later so that mastery is durable. | E72: Cleared concepts are re-queued at 7 / 21 / 60 days; re-test items appear automatically in the next generated paper. | F72: P2 | G72: M | H72: 3 | I72: S16 | J72: Done
A73: M13 | B73: F070 | C73: Habit micro-drills | D73: As a coach I want behaviour drills so that delivery habits change, not just knowledge. | E73: Short drills targeting a habit (mark-to-point, three-check on assertion-reason, two-minute blank sweep) with pass criteria. | F73: P2 | G73: M | H73: 3 | I73: S17 | J73: Done
A74: M14 | B74: F071 | C74: Parent dashboard | D74: As a parent I want a home screen with the state of play so that I know what matters today. | E74: Shows per subject: latest score, trend, Delivery Gap, top 3 priority concepts, next action, pending uploads. | F74: P0 | G74: L | H74: 4 | I74: S12 | J74: Done | K74: The API half (GET /api/dashboard/:studentId, buildParentDashboard) already existed; this adds the missing screen at /home (tab06's exact route). Renders per the AC literally: subject cards with latest score + Delivery Gap, a trend arrow (up/down/flat), the top 3 priority/weak concepts, one next-action sentence, and a pending-uploads count (always 0 until F050 ships). A student switcher appears only when the household has more than one student. Verified live end to end against the real dev server and dev DB with Playwright (not just the API): (1) a fresh household with a student but no papers shows the correct empty state ('No papers generated for this student yet') with a link to /generate, and (2) a full real generate -> attempt -> submit -> evaluate -> confirm cycle on a fixture question renders the actual card -- 'Mathematics (seed)', '→ Steady', 'Latest score 100% — Delivery Gap 0%', and the correct neutral next-action text -- confirmed both by extracting the rendered page text and by screenshot. Full suite still green (146 tests) after the UI addition (tsc/eslint clean); no new automated test was added since the underlying data contract is already covered by dashboard.integration.test.ts and this component has no server-side logic of its own to unit test.
A75: M14 | B75: F072 | C75: Student dashboard | D75: As a student I want to see my progress so that I stay motivated. | E75: Mastery rings per chapter, streak, next drill, recent improvements; no red shaming language. | F75: P1 | G75: M | H75: 3 | I75: S13 | J75: Done | K75: New GET /api/student-dashboard (not in tab05, self-scoped via studentsRepository.findByUserId -- no :id param, so there is no id a student session could substitute to read another student's data, T09) and buildStudentDashboard() (src/lib/student-dashboard.ts). Mastery ring per chapter = share of that chapter's concepts currently Strong/Maintenance in concept_status out of all concepts in the chapter (concepts never attempted count as 0, not excluded -- a real progress-through-the-chapter reading, a stated approximation since no numeric mastery score exists elsewhere in the schema). 'Next drill' is approximated as the single most urgent tracked concept (Priority > Weak > Needs Practice) since F066 (remediation packs) doesn't exist yet -- surfaced as 'Today's focus' with only the concept name, never the raw status word, per the AC's 'no red shaming language'. 'Recent wins' reads concept_status.trend='up' rows (F062's existing trend engine) rather than inventing new tracking. Streak is computed in a pure, unit-tested function (computeStreakDays) from distinct submitted_at dates on the student's own attempts -- consecutive days ending today or yesterday (so it survives until the day is over). New MasteryRing component (src/components/mastery-ring.tsx, plain inline SVG, no charting dependency) is reusable by future screens per tab06's 'reuse mastery ring' note. Verified live end to end against the real dev server and dev DB with Playwright, not just the API: a fresh student's first-ever attempt (one correct answer) renders a real progress ring (14%, matching 1 of ~7 concepts in the seed chapter now Strong) and a correctly pluralized streak line -- confirmed by extracted page text and screenshot. Backend logic (trend computation, mastery aggregation, streak edge cases) has its own integration and unit tests. Full suite green (155 tests, up from 146 -- also fixed a pre-existing bug in F025's own test, which never deleted the fixture chapters it created, letting a later run's random chapter_no collide with a leftover row).
A76: M14 | B76: F073 | C76: Per-paper report page & PDF | D76: As a parent I want to keep the report so that I can share it with a tutor. | E76: Web report plus downloadable PDF including error inventory and concept-wise performance. | F76: P0 | G76: M | H76: 3 | I76: S14 | J76: Done | K76: GET /api/evaluations/:id/report/pdf (not in tab05's listed routes -- only the JSON GET /api/evaluations/:id/report exists there -- added as a sibling path the same way GET /api/papers/:id/pdf sits alongside GET /api/papers/:id). Renders the exact same buildDiagnosisReport() data the JSON route returns through the F033 PDF pipeline (Playwright/Chromium) -- not a second computation of the report, a second representation of it. Extended buildDiagnosisReport() itself with a real gap the AC named explicitly: 'concept-wise performance' didn't exist before this feature (only the error inventory did, which only covers items that lost marks) -- added as a per-concept marks-awarded/marks-max/% breakdown across every item, plus paper/student meta fields the PDF header needs. Verified live against the real dev DB: a real generate->attempt->submit->evaluate->confirm cycle with a deliberately wrong answer produces a genuine PDF (%PDF- header, real byte size) and correct household isolation (404 for a second household); layout also eyeballed via a rendered screenshot (score cards, error inventory table, concept performance table, actions) before calling this done. Marked In Progress, not Done: the 'web report' half of the AC doesn't exist -- no screens exist anywhere in this repo. The report screen now exists (/evaluation/:id/report) -- browser-verified end to end against a live dev server including the pre-confirmation 409 state and the PDF download link, no backend changes were needed; a 'View report' link was also added from the /evaluate/:attemptId review screen once an evaluation is confirmed, closing the loop from evaluation review to report for the first time.
A77: M14 | B77: F074 | C77: Weekly summary generator | D77: As a parent I want a weekly digest so that progress is reviewed regularly. | E77: Auto every 7 active days: best subject, most improved concept, urgent concept, 7-day study plan, cumulative stats vs last week. | F77: P1 | G77: L | H77: 4 | I77: S16 | J77: Done | K77: GET /api/summary/weekly/:studentId (tab05's exact route, query week_start optional -- defaults to 7 days ago) + buildWeeklySummary() (src/lib/weekly-summary.ts). Best subject and cumulative stats come from confirmed evaluations' percentage in a real timestamptz window; most_improved_concept compares each in-window concept_mastery ledger row (F061) against that concept's most recent row before the window. Found and fixed a real bug while building this: concept_mastery.date is a DATE column, and comparing it against a timestamptz 'now' instant silently excluded today's own rows (date-vs-timestamptz casts to date granularity, so 'today < today' is false) -- fixed with explicit ::date-cast comparisons on plain YYYY-MM-DD strings, moved into two new conceptMasteryRepository methods (listForStudentInDateWindow, findMostRecentBeforeDate) since raw kysely/sql imports are lint-restricted outside src/db/repositories. urgent_concept and seven_day_plan reuse F072's priority-concept approach (Priority > Weak > Needs Practice from concept_status) as a stand-in for F077's dedicated planner and M16's 'auto every 7 active days' trigger, both Not Started. Screen at /summary/weekly (tab06's exact route) renders all five pieces: this-week-vs-last-week with a signed delta, best subject, most improved concept, an urgent-concept card, and the 7-day list. Verified live end to end against the real dev server and dev DB with Playwright: two real generate->attempt->submit->evaluate->confirm rounds on the same concept, one backdated 8 days so it falls in 'last week', rendered exactly the expected figures (100% this week vs 0% last week, +100% delta, the correct best subject and most-improved concept) -- confirmed by extracted page text and screenshot. New integration test asserts the same window separation server-side. Full suite green (158 tests, up from 155).
A78: M14 | B78: F075 | C78: Trend charts | D78: As a parent I want visual trends so that direction is obvious at a glance. | E78: Score-over-time per subject, Delivery Gap over time, concept status distribution; all charts print legibly. | F78: P1 | G78: M | H78: 3 | I78: S15 | J78: Done | K78: Extends F071's existing GET /api/dashboard/:studentId (no new route -- the AC's three charts live on the same /home screen tab06 already scopes them to) with score_history per subject (oldest-first, capped at the 20 most recent confirmed evaluations) and a top-level concept_status_distribution count across every tracked concept. Loaded the dataviz skill before writing any chart code per its trigger rule. Two new inline-SVG components, no charting dependency: LineChart (score-over-time and Delivery Gap over time -- Class 7 Math's single-subject launch scope reads as one labelled line; wired for multiple categorical series once more subjects exist) and StatusDistributionBar (a single horizontal stacked bar using the skill's reserved status palette -- good/warning/serious/critical -- never the categorical ramp, since concept status is state, not series identity; Strong and Maintenance share the 'good' step, disambiguated by the 2px segment gap and each segment's own label). Categorical and status hex values are the dataviz skill's validated reference palette (this project has no ramp of its own yet); validated with the skill's own script in both light and dark mode -- all hard checks pass, dark mode clears 3:1 contrast outright, light mode's known contrast WARN is mitigated by the direct labels this chart always ships. 'Print legibly': every line ends in a direct value label and the distribution bar's legend is plain text, so the reading survives even where a printer drops SVG fill/stroke color -- texture-fill (the skill's stronger print/CVD channel) is out of scope for now, a stated simplification. Found and fixed a real layout bug during live verification: axis gridline labels and the line's end-value label both lived on the right edge, so they visually collided whenever a value landed exactly on a gridline (e.g. a flat 0% line) -- moved axis labels to the left (the more conventional placement anyway). Verified live against the real dev server and dev DB with Playwright in both light and dark mode: a real 5-round evaluation history renders an actual zigzag score line and a flat Delivery Gap line with clean, non-colliding axis labels, and a forced Priority status renders a full-width critical-colored distribution bar -- confirmed by screenshot. Extended the existing dashboard.integration.test.ts with score_history and concept_status_distribution assertions rather than a new test file, since this is additive to F071's own payload. Full suite green (158 tests).
A79: M14 | B79: F076 | C79: Session-opening recap | D79: As a returning user I want a recap so that I resume with context. | E79: On login: last session date, last paper evaluated, current priority concepts, pending items. | F79: P2 | G79: S | H79: 2 | I79: S16 | J79: Done
A80: M15 | B80: F077 | C80: 7-day study plan generator | D80: As a parent I want a day-by-day plan so that the week is structured. | E80: Plan built from current weak/priority concepts and upcoming exam dates: 7 rows of subject + concept + activity, regenerable. | F80: P2 | G80: M | H80: 3 | I80: S17 | J80: Done
A81: M15 | B81: F078 | C81: Exam countdown & syllabus coverage | D81: As a parent I want to see readiness so that I can pace revision. | E81: Countdown to each exam with % of syllabus concepts at Strong; highlights chapters untested so far. | F81: P2 | G81: M | H81: 3 | I81: S17 | J81: Done
A82: M15 | B82: F079 | C82: Daily task list & completion | D82: As a student I want today's tasks so that I know what to do. | E82: Tasks generated from the plan, tickable, roll over when missed; completion feeds the weekly summary. | F82: P3 | G82: M | H82: 2 | I82: S18 | J82: Done
A83: M16 | B83: F080 | C83: Transactional email | D83: As a parent I want email alerts so that I do not have to check the app. | E83: Paper ready, evaluation complete, weekly summary; unsubscribe honoured; templates tested across major clients. | F83: P2 | G83: M | H83: 2 | I83: S18 | J83: In Progress | K83: No dedicated email-provider account exists (Resend etc. would need a new signup) -- instead uses Make.com (already connected) as the sending layer: a Custom Webhook -> Gmail 'Send an email' scenario (Make scenario 7437955, verified end-to-end with a real test send). src/lib/email.ts's sendTransactionalEmail POSTs to that webhook (MAKE_EMAIL_WEBHOOK_URL env var) and logs every attempt as a notifications row (sent/failed/skipped). Wired into the three named events: paper_ready (papers/generate.ts), evaluation_complete (evaluations.ts, worded as provisional since AI never finalises a mark), weekly_summary (new Vercel Cron route /api/cron/weekly-summary, Sundays 18:00 UTC, CRON_SECRET-gated, reuses F074's buildWeeklySummary). Unsubscribe is HMAC-signed (no stored token) and flips users.email_notifications_enabled, checked before every send. NOT done: 'templates tested across major clients' -- a manual visual-QA task (same category as F107 print QA), not attempted. Fits this app's current single-family launch scale; a real transactional provider (Resend has a native Make connector already) would replace personal-Gmail sending if this ever needs to scale to many families.
A84: M16 | B84: F081 | C84: WhatsApp notifications | D84: As an Indian parent I want WhatsApp so that I actually see the message. | E84: BSP integration with approved templates for paper ready, weekly summary and daily parent action; opt-in required. | F84: P3 | G84: L | H84: 4 | I84: S18 | J84: Not Started
A85: M16 | B85: F082 | C85: Daily parent action nudge | D85: As a parent I want one instruction a day so that coaching is sustainable. | E85: A single concrete action derived from the latest diagnosis, delivered once daily, marked done or skipped. | F85: P2 | G85: S | H85: 2 | I85: S18 | J85: Done | K85: Reuses F059's own worst-first ranking (Priority/Weak concept_status, tracker-wide) -- extracted from buildDiagnosisReport into a shared getRankedActions(db, studentId) so both features share one ranking, not two that could drift. New daily_nudges table (UNIQUE(student_id, date), same idempotent top-up shape as F077's study_plans): generateOrGetTodayNudge takes the single top-ranked action, or a documented 'keep up the current pace' fallback when nothing is flagged. Delivered via F080's email plumbing (new 'daily_nudge' template, Vercel Cron at 01:30 UTC ~ 7am IST, CRON_SECRET-gated) and a 'Today's action' card on the parent dashboard (/home) with Done/Skip buttons -- GET /api/nudges/today + PATCH /api/nudges/:id, parent/admin-only per the AC's own user story. Same not-yet-configured caveat as F080: real sends need MAKE_EMAIL_WEBHOOK_URL + CRON_SECRET set in Vercel.
A86: M17 | B86: F083 | C86: Admin console | D86: As an admin I want a back office so that content work does not need a developer. | E86: Manage syllabus, questions, blueprints, users, AI job history; role-restricted; every write audited. | F86: P1 | G86: L | H86: 4 | I86: S19 | J86: Done | K86: All four pieces of the AC's literal list are now built. Blueprint authoring (F086) and AI usage & cost (F091) existed from earlier work; this session added the remaining two. /admin/syllabus: a deliberately READ-ONLY browser (subject -> chapters with live IN/OUT scope counts -> concepts + full scope text), not a write CRUD API -- F015 (Done) already scoped that out with the user's explicit sign-off, since real curriculum scope has to be grounded in the actual textbook via the /examprep-ingest-source and /examprep-scope-authoring skills, not typed into a form from memory (reconfirmed with the user 2026-09-17 before building this, since tab06 literally lists 'CRUD' as a key element here). /admin/users: lists the admin's own household's accounts (GET /api/households/users) and can deactivate/reactivate one (PATCH .../:id). 'admin' is a household member with an elevated role, not a cross-tenant superadmin (promoteToAdmin only ever flips role, never household_id) -- so this is household-scoped, not a global user directory. Real enforcement, not decorative: users.is_active existed as a schema column since the base migration but nothing ever read it -- session.ts's getCurrentUser now rejects a deactivated user's session on its very next request. Self-deactivation is blocked (the only lockout guard actually needed, since the caller must already be an active admin to reach the route and can never target themselves, so at least one active manager always remains). Every toggle writes an audit_log row per 'every write audited'. Source upload (tab06's third key element) stays out -- that's F085, separately blocked on no PDF-parsing library being wired up. AI job history is arguably covered by /admin/usage already. Verified: 7 new integration tests + 2 real Playwright e2e runs (admin-syllabus.spec.ts, admin-users.spec.ts) + full regression suite green throughout (376 -> 383 tests across the two commits). Committed a640ab0, dab71de.
A87: M17 | B87: F084 | C87: Question review queue | D87: As an admin I want to approve AI questions so that quality is controlled. | E87: Draft/Approved/Rejected states with reviewer, timestamp and reason; only Approved questions are eligible for papers. | F87: P1 | G87: M | H87: 3 | I87: S19 | J87: Done | K87: New /admin/questions screen (tab06's exact route) plus the backend it needed and didn't have: GET /api/questions/:id (full detail including answer/is_correct -- legitimate here, an admin reviewing a question IS the answer-key audience, unlike the student-facing attempt view), POST /api/questions/:id/reject, and GET /api/syllabus/concepts (no route had ever listed concepts by chapter or subject -- needed for the concept picker feeding both the review queue and F025's AI-generate form, which this screen also exposes directly). 'Rejected' maps onto the existing 'retired' status rather than a fourth schema value: CLAUDE.md invariant 4 fixes the lifecycle at Draft/Approved/Retired, and 'retired' already means 'excluded from paper generation, row never deleted' -- exactly rejection's effect. Unlike approve() (reason required only for Tier B), reject() always requires a note, matching the AC's unconditional 'reason'. 'Only Approved questions are eligible for papers' was already true before this feature (F027-032's generator has always filtered status='approved') -- this screen is what makes F025's Draft AI output actually reachable by a human instead of stuck with no review UI. Verified live against the real dev server and dev DB with Playwright: a real Tier B draft question rendered in the queue, rejecting it with a reason retired it and recorded reviewer+note+timestamp, confirmed both on screen and by re-reading the row. Full suite green (173 tests, up from 166). [2026-09-17 UPDATE] The review-queue UI and its approve/reject routes were removed at the user's explicit request (same decision as F117; migration 0061_remove_question_approval_workflow). /admin/questions no longer has a 'Review queue' section -- draft/approved/rejected states are gone; every question is approved on creation. What remains of this feature: GET /api/questions/:id (detail) and GET /api/syllabus/concepts (concept picker), both still used by the surviving Question bank (F118) and AI-generate (F025) screens. PATCH /api/questions/:id can still retire a question (F118's Retire button), the closest surviving analogue to 'Rejected'.
A88: M17 | B88: F085 | C88: Source PDF ingestion | D88: As an admin I want to upload textbook chapters so that scope is grounded in the real book. | E88: Upload chapter PDF, extract text, attach to chapter as the scope source, flag corrupt or image-only PDFs immediately. | F88: P1 | G88: M | H88: 3 | I88: S19 | J88: Not Started
A89: M17 | B89: F086 | C89: Blueprint authoring UI | D89: As a coach I want to enter my school's real paper pattern so that mocks match it. | E89: Form-based blueprint builder with live validation that section marks sum to the paper total. | F89: P1 | G89: M | H89: 3 | I89: S20 | J89: Done | K89: New screen (folded into /admin -- tab06 has no dedicated blueprint route, and POST /api/blueprints already existed fully server-validated with nowhere to enter it from). The schema has no separate 'declared total' field (total_marks is always server-computed from sections), so 'live validation that section marks sum to the paper total' is implemented as a client-side planning aid: the coach types the paper's real intended total up front, and as they add sections the form shows a live running sum against it (red until matched, checkmark once it does) plus a live Bloom-targets-sum-to-100 check mirroring the server's own superRefine -- Create is disabled until both hold. Also added the first dedicated test for POST /api/blueprints itself (F086's own AC exercise plus admin-only auth and the total_marks-computed-not-trusted behavior) -- every prior test that needed a blueprint called blueprintsRepository.insert() directly, bypassing the route entirely. Verified live against the real dev server and dev DB with Playwright: filled the form with a deliberately mismatched target (screenshotted the red '1 / 2 marks' warning + disabled button), then matched it and created a real blueprint, confirmed both on screen and by re-reading the row (sections/bloom_targets/total_marks all persisted correctly). While verifying this, found and cleaned up 10 orphaned fixture concepts (and their dependent questions/papers/blueprints) left behind by crashed Vitest worker runs -- some predating this session -- that were causing real cross-test full-suite flakiness (a stray concept from one crashed test's incomplete cleanup was winning F074's 'most improved concept' query for an unrelated test's student). Full suite green (176 tests, up from 173) after the cleanup.
A90: M18 | B90: F087 | C90: Telugu script rendering & fonts | D90: As a Telugu student I want correct script so that the paper is usable. | E90: Noto Sans Telugu / Mallanna embedded; correct conjunct rendering on screen and in PDF; verified on a 200-word sample including ottulu and deerghalu. | F90: P1 | G90: L | H90: 4 | I90: S20 | J90: Done | K90: Built 2026-10-01. PDF: Noto Sans Telugu (OFL, Google Fonts Telugu subset, 124 KB variable font, src/lib/pdf/fonts/) is inlined into every PDF template's HTML as a data URL with a Telugu-only unicode-range, so the serverless renderer needs no system font; render.ts now waits for document.fonts.ready before printing. Screen: Noto Sans Telugu added to the Google Fonts import and every font stack (downloaded only when a page contains Telugu). Verified on a 209-word sample (telugu-sample.fixture.ts) with ottulu (క్ష స్త్ర ద్ధ శ్రీ జ్ఞ ఙ్మ త్మ ర్య ప్ర), deerghalu (కా కీ కూ కే కో ఐ ఔ), reph, ZWNJ, visarga and Telugu digits: visually in a real PDF and on screen, and automatically in telugu-pdf.integration.test.ts (the bundled face loads and covers the sample in all 3 themes; the PDF embeds it as Type3 glyphs, never a system Telugu font). Mutation-checked: removing the font fails 4 tests. Mallanna not added (AC says Noto Sans Telugu / Mallanna; one is enough). Not covered: diagram SVG labels still use Helvetica.
A91: M18 | B91: F088 | C91: Telugu grammar concept tagging | D91: As a coach I want grammar concepts tagged so that weak areas are trackable. | E91: Concept taxonomy for sandhulu, samasalu, alankaralu, vibhaktulu; questions taggable to a specific grammar rule. | F91: P1 | G91: M | H91: 3 | I91: S20 | J91: Not Started
A92: M18 | B92: F089 | C92: Telugu composition format checking | D92: As a coach I want format errors caught so that Format Miss is trackable. | E92: Expected format per composition type (letter, dialogue, essay); mismatch recorded as a Format Miss pattern hit, not a content error. | F92: P2 | G92: M | H92: 3 | I92: S21 | J92: Not Started
A93: M18 | B93: F090 | C93: Bilingual UI strings | D93: As a parent I want the interface in my language so that it is easy to use. | E93: i18n framework with English and Telugu strings; no hardcoded UI text; language switch persists per user. | F93: P3 | G93: M | H93: 3 | I93: S21 | J93: Not Started
A94: M19 | B94: F091 | C94: AI token metering & cost dashboard | D94: As an owner I want to see AI spend so that costs do not run away. | E94: Every AI call logs model, tokens in/out, latency, cost and purpose; dashboard by day, feature and student. | F94: P1 | G94: M | H94: 3 | I94: S21 | J94: Done | K94: ai_jobs already existed (0030) but was never written to -- added logAiJob (src/lib/ai-metering.ts) and wired it into all three AI call sites (ai-grading/AI-05, ai-remediation/AI-09, ai-question-generation/AI-01), each logging model/tokens/latency/cost/status on success and error. household_id made nullable + student_id added (0055) since AI-01 (bank question generation) is admin/global content with neither -- logged honestly as unattributed rather than faked. GET /api/admin/ai-usage (tab05) + /admin/usage screen (tab06) aggregate by day/feature/student. Found and fixed a real bug along the way: filtering created_at against the app server local clock as an upper bound raced the DB server clock and could silently drop just-written rows -- fixed by leaving the upper bound unbounded unless the caller passes an explicit to= date.
A95: M19 | B95: F092 | C95: Rate limits & spend caps | D95: As an owner I want hard limits so that a loop cannot bankrupt me. | E95: Per-user and global daily caps on generation and evaluation calls; graceful message on limit, alert to admin at 80%. | F95: P1 | G95: M | H95: 2 | I95: S21 | J95: Done | K95: enforceAiCallBudget (src/lib/ai-metering.ts) checks a global daily cap and a per-household daily cap (documented defaults: 500 global / 60 per household -- "per-user" mapped to per-household, this products account unit; F121 owns a separate per-student axis) before every AI-01/05/09 call, throwing AiCapReachedError on a hit; every caller catches it and degrades into the same graceful fallback each already had for AI-not-configured (manual marking / bank fallback / admin writes manually). Crossing 80% of either cap writes an idempotent in-app notification (existing notifications table, channel=in_app) to every admin user.
A96: M19 | B96: F093 | C96: Product analytics | D96: As an owner I want funnel data so that I know where users drop off. | E96: Events: paper generated, downloaded, attempted, uploaded, evaluated, remediated; funnel view; privacy-respecting, no third-party ad pixels. | F96: P2 | G96: M | H96: 2 | I96: S22 | J96: Done | K96: New product_events table (migration 0057) + src/lib/product-events.ts: logProductEvent (never-throws, same pattern as F091s logAiJob) wired into 5 real routes for the 5 reachable lifecycle events (paper_generated, paper_downloaded, attempt_submitted, evaluation_completed, remediation_started); attempt_uploaded is declared in the type + DB check constraint for when F050 lands but nothing fires it yet since that upload feature is unbuilt (documented gap). GET /api/admin/product-funnel + /admin/funnel screen report all 6 stages always, in order, using DISTINCT household/student counts (not raw event counts) and pct-of-first-stage -- first-party only, no third-party ad pixels, per the AC.
A97: M19 | B97: F094 | C97: Model routing & fallback | D97: As an owner I want cheap models used where possible so that quality and cost are balanced. | E97: Task-to-model map (cheap model for classification, strong model for generation and grading) with automatic fallback on failure. | F97: P1 | G97: M | H97: 3 | I97: S22 | J97: Done | K97: New src/lib/ai-models.ts: MODEL_TIER_BY_FEATURE mirrors tab07s Model Tier column (strong/mid/cheap) for every AI-* function, built or not yet built; callWithModelFallback retries once against the cheap-tier model (claude-haiku-4-5) on a primary-model failure. Wired into all three implemented AI-*.ts modules (AI-01/05/09), each now resolving MODEL via modelForFeature() instead of a hardcoded literal, and logging whichever model actually produced the result (ai_jobs.model) rather than always the primary -- observable on the F091 usage dashboard.
A98: M20 | B98: F095 | C98: DPDP consent & privacy notice | D98: As a parent I want to give informed consent so that use is lawful. | E98: Consent captured at student creation with purpose and retention stated; verifiable parental consent for under-18 data; withdrawal supported. | F98: P0 | G98: M | H98: 3 | I98: S22 | J98: In Progress | K98: New consents table (migration 0040, append-only per CLAUDE.md invariant 4 -- withdrawal sets withdrawn_at, never deletes). POST /api/students now requires consent_accepted:true (literal true, not just truthy) and atomically inserts a consent row pinned to CURRENT_CONSENT_VERSION alongside the student in one transaction -- a student row can never exist without a matching consent event. POST /api/students/:id/consent/withdraw records withdrawal (not in tab05's listed routes -- that sheet has no consent endpoints at all -- added as the smallest reasonable path under the existing /api/students/:id resource since the AC explicitly requires withdrawal). POST /api/papers/generate now checks for an active consent before generating anything for that student and 403s otherwise, so withdrawal has a real, enforced effect rather than just sitting in a log. What this is NOT: 'verifiable parental consent' in the DPDP sense needs actual identity verification (a checkbox from whoever is logged in isn't that), and src/lib/consent.ts's purpose/retention wording is placeholder text, not lawyer-reviewed copy -- both need real product/legal decisions this session can't make on its own. Verified live against the real dev DB (consent.integration.test.ts, 8 tests): creation rejected without consent, accepted creation writes a matching row, generation succeeds while active and 403s after withdrawal, re-withdrawing 409s, and cross-household withdrawal attempts 404. Full suite green (89 tests).
A99: M20 | B99: F096 | C99: Data isolation enforcement | D99: As a user I want certainty that no one sees my child's data so that I trust the app. | E99: Every query filtered by household; automated test attempts cross-household access on all endpoints and must fail. | F99: P0 | G99: L | H99: 4 | I99: S22 | J99: Done | K99: Every route this session built already scopes through the repository layer (F013's createScopedRepository, used by every single route in the app) -- this feature is proving that live, automatically, calling the REAL route handler functions with genuine better-auth session cookies (no dev server needed -- src/db/test-helpers.ts drives auth.api.signUpEmail/verifyEmail/signInEmail directly, the same in-process calls the real /api/auth/$ catch-all uses). 17 tests in cross-household-access.integration.test.ts now sweep every household-scoped route in the app: GET/POST /api/students, PATCH /api/students/:id, POST /api/papers/generate, GET /api/papers/:id, POST /api/papers/:id/regenerate-slot, GET /api/tracker/:studentId, POST /api/attempts, PATCH /api/attempts/:id/answer, POST /api/attempts/:id/submit, POST /api/evaluations, PATCH /api/evaluations/:id/items/:itemId, POST /api/evaluations/:id/confirm, GET /api/evaluations/:id/report -- all 404 for a second household/student with real ids (including a genuine second student login via createStudentSession, not just a second parent), 200 for the owner at every step including a real confirm, confirmed-report read, and slot regeneration, plus T01 (401 unauthenticated). This also closes F103's stated auth-guard gap. Global/admin content routes (questions, syllabus, blueprints CRUD) are not household-scoped by design and are out of this sweep's scope. Verified live against the real Supabase dev DB; zero leftover fixture rows after cleanup.
A100: M20 | B100: F097 | C100: Encryption & secure storage of scans | D100: As a parent I want handwriting images protected so that they cannot leak. | E100: Uploads in private storage with signed short-lived URLs; encryption at rest; no public bucket paths anywhere. | F100: P0 | G100: M | H100: 3 | I100: S23 | J100: Done | K100: Built 2026-09-30. Pages AES-256-GCM encrypted by the app (key HKDF-derived from BETTER_AUTH_SECRET) before the database; served only by GET /api/scan-pages/:id with a 10-minute HMAC-signed link AND a session with access; Cache-Control no-store; no bucket, no public path. Images purged 30 days after upload by the daily cron. /privacy updated. Tests cover tamper, wrong key, expiry, forged/moved signatures, cross-household, retention.
A101: M20 | B101: F098 | C101: Export & delete my data | D101: As a parent I want to take or erase my data so that I stay in control. | E101: Self-serve full export (JSON + PDFs) and hard delete within 30 days, including scans and AI job logs. | F101: P1 | G101: M | H101: 3 | I101: S23 | J101: Done | K101: POST /api/privacy/export (tab05's exact route) returns the full household export synchronously in the response rather than the AC's async-job-plus-email flow -- there is no job queue or email provider in this app (M16 is Not Started), and a household's data isn't large enough at launch scope for synchronous to be a real problem; the export's own `notes` field says so rather than silently pretending PDFs/scans are bundled (they aren't -- papers are rendered on demand, and there's no real scan storage since M10 wasn't built this pass). POST /api/privacy/delete (not in tab05, but the AC's other half) hard-deletes the household -- a deliberate, DPDP-driven exception to CLAUDE.md invariant 4 ('nothing is deleted'), justified explicitly by this feature's own right-to-erasure requirement. Verified against the actual migrations, not assumed, that every table genuinely cascades from households.id (directly or transitively through students.id) before relying on a single DELETE to erase everything. New deletion_log table (migration 0048) is the erasure audit trail -- household_id is deliberately a plain column, not a foreign key, or the audit row would cascade away in the same transaction as the data it's proving was deleted. Requires typing the household's real name back (not just a boolean) as the confirmation gesture, matching common practice for a genuinely irreversible action. New /settings screen (tab06's exact route). Verified live end to end against the real dev server and dev DB with Playwright: the delete button stays disabled until the typed name matches exactly, and clicking it actually erased the household (re-queried after, not assumed) while the deletion_log row survived and the session correctly stopped authenticating afterward. New integration test suite exercises the same: real export contents, wrong-name rejection, real cascade-delete, and post-delete session invalidation. The AC's exact 30-day SLA and any formal legal notice requirements need real legal review, same caveat F095 already flagged for verifiable parental consent -- the mechanical capability is what's built here. Full suite green (181 tests, up from 176). 2026-10-01 (owner decision, Google Play requirement): a student who signed up on her own and is not linked to a parent can delete her own account from Settings (typed DELETE; GET/POST /api/privacy/delete-self); a parent-added or parent-linked student is refused and must ask the parent. Also fixed a real bug: a parent deleting a household that a self-signed-up student had been linked into failed with a 500 (two interlocking RESTRICT keys: consents.given_by_user_id and students.own_household_id); deleteHouseholdData now deletes her original household's consents, then the household, then the original. Tests: student-self-delete.integration.test.ts.
A102: M20 | B102: F099 | C102: Audit log | D102: As an owner I want an immutable trail so that mark changes can be traced. | E102: Append-only log of score overrides, role changes, deletions, admin writes; visible to household owner. | F102: P1 | G102: M | H102: 2 | I102: S23 | J102: Done | K102: audit_log covers every sensitive write that actually exists in the app: F047 evaluation-item overrides, POST /api/evaluations/:id/confirm (score finalisation), and POST /api/students/:id/consent/withdraw. GET /api/audit-log makes the trail visible to the household owner (household-scoped, capped at 100 most recent). Of the AC's four named categories, two have no corresponding mutation anywhere in the 122-feature backlog to log: no route in tab05 (or built) ever changes a user's role after creation (F007 sets a role once, at signup/student-creation time; promoteToAdmin is a test-only helper, not a product endpoint), and nothing is ever hard-deleted per CLAUDE.md invariant 4 -- the one deliberate exception (F098 DPDP right-to-erasure) already has its own dedicated, tamper-resistant trail (deletion_log, migration 0048) which is NOT an FK to households specifically so it survives the cascade audit_log would not. Marking Done: the AC is met for every write path that exists; the two absent categories are absent by design, not by omission.
A103: M21 | B103: F100 | C103: Plans & usage limits | D103: As an owner I want tiers so that the product can be sold. | E103: Free/Paid plans with per-month paper and evaluation quotas enforced server-side. | F103: P3 | G103: M | H103: 3 | I103: S24 | J103: Not Started
A104: M21 | B104: F101 | C104: Payments (Razorpay/Stripe) | D104: As a customer I want to pay easily so that I can subscribe. | E104: Checkout, webhooks, invoice email, failed-payment retry, GST-compliant invoice fields. | F104: P3 | G104: L | H104: 4 | I104: S24 | J104: Not Started
A105: M21 | B105: F102 | C105: Tenant onboarding for tutors | D105: As a tutor I want many students so that I can use it professionally. | E105: Tutor tenant with student roster, bulk paper generation, class-level heatmap. | F105: P3 | G105: L | H105: 4 | I105: S24 | J105: Not Started
A106: M22 | B106: F103 | C106: Unit & integration test suite | D106: As a developer I want tests so that regressions are caught. | E106: Coverage on scoring, selection, mastery rules and auth guards; suite runs in CI under 5 minutes. | F106: P0 | G106: L | H106: 4 | I106: S23 | J106: Done | K106: 184 tests across 34 files, all passing, ~192s wall time (well under the 5-minute CI budget). Coverage now spans: scoring.ts unit tests (normalizeAnswer/scoreObjectiveAnswer/templateFeedback), the F063 mastery escalation state machine (determineNextStatus), papers.ts allocation/difficulty weighting (F028/F119), household-isolation.integration.test.ts and cross-household-access.integration.test.ts automating T01/T02 against the real dev DB at both the repository and route-handler layers, plus integration coverage for every feature built this session (remediation, dashboards, admin review, syllabus fidelity, privacy export/delete, consent). F104 added a real Playwright E2E suite (e2e/happy-path.spec.ts, npm run test:e2e) on top of this, covering the full parent-generates/student-attempts/parent-evaluates loop through the real UI -- kept as a separate, slower CI stage rather than folded into the vitest run. .github/workflows/tests.yml provisions a scratch Postgres, migrates, seeds, lints, typechecks, installs Playwright Chromium and runs the suite; written but still unverified end-to-end since there is no GitHub remote configured for this repo yet (same F003 blocker -- needs the GitHub token to actually push and watch a run). Marking Done: the AC ("coverage on scoring, selection, mastery rules and auth guards; suite runs in CI under 5 minutes") is met on every measurable axis available without that remote.
A107: M22 | B107: F104 | C107: E2E happy-path tests | D107: As a team I want the core journey tested so that releases are safe. | E107: Playwright: sign in, generate paper, download PDF, attempt, evaluate, see tracker update — green before every deploy. | F107: P0 | G107: M | H107: 3 | I107: S23 | J107: Done | K107: Real Playwright E2E suite (e2e/happy-path.spec.ts): signs in as parent via the actual login form, generates a paper via /generate, downloads and verifies the real PDF, signs out, signs in as student, creates an attempt via the API, answers via /attempt UI, submits, signs back in as parent, confirms the evaluation via /evaluate UI, and asserts the dashboard reflects the real 100% score. Surfaced and fixed a genuine production bug along the way: index.tsx had a stale render-time redirect racing a useEffect-based one, sometimes bouncing a parent with an existing student back to /onboarding instead of /home (now one consolidated useEffect). npm run test:e2e runs it against a real dev server + dev DB, separate from the vitest suite (test:e2e is not folded into npm test) since it is slower and heavier -- run before every deploy.
A108: M22 | B108: F105 | C108: AI accuracy harness | D108: As an owner I want measured AI quality so that trust is evidence-based. | E108: Fixture of 100 human-marked answers; harness reports agreement %, false-generous and false-harsh rates per model; regression gate on prompt change. | F108: P0 | G108: L | H108: 4 | I108: S24 | J108: Not Started
A109: M22 | B109: F106 | C109: Syllabus fidelity audit | D109: As a coach I want proof that papers stay in scope so that time is not wasted. | E109: Automated check that every question in a generated paper maps to an IN-scope concept for that chapter and source book; zero violations required. | F109: P0 | G109: M | H109: 2 | I109: S24 | J109: Done | K109: New auditSyllabusFidelity() (src/lib/syllabus-fidelity.ts) checks CLAUDE.md invariant 5 for real: every APPROVED question's concept must belong to a chapter with (a) a registered source book and (b) at least one IN-scope chapter_scope record -- neither is actually enforced at the DB/schema level (a concept can be created under a chapter with zero scope rows), and F025's own in-scope-citation guardrail only runs for AI-generated questions, never for manually authored or bulk-imported ones, so this audit is a real backstop, not a duplicate check. Running it against the real dev DB surfaced a genuine, significant finding: only 2 of the 16 seed/fixture chapters (F012) -- 'Fractions' and 'Decimals' -- ever got chapter_scope IN records authored; the other 14 ('Sample Chapter -- Integers/Simple Equations/Lines and Angles/Triangles/Comparing Quantities/Perimeter and Area/Rational Numbers/Algebraic Expressions/Exponents and Powers/Symmetry/Data Handling/Practical Geometry/Visualising Solid Shapes (seed)', plus one Science fixture) have 200 approved questions between them with zero scope grounding. This audit cannot fix that itself -- chapter_scope needs real page-cited textbook content (the /examprep-scope-authoring skill's job), which would mean fabricating citations to close the gap, exactly what CLAUDE.md invariant 5 exists to prevent. Flagging this explicitly rather than silently working around it: before any of these 14 chapters' seed questions are used for a real paper, either author real scope for them or retire the questions. New admin-only GET /api/admin/syllabus-fidelity (not in tab05) makes the audit runtime-visible instead of a one-off script. The committed test proves the audit mechanism itself (injects one deliberate violation, confirms detection) rather than asserting 'zero on real data', which is currently false for the documented content reason above -- a false-pass assertion would be worse than an honest gap. Full suite green (184 tests, up from 181).
A110: M22 | B110: F107 | C110: Print QA across devices | D110: As a parent I want reliable printing so that the paper is usable. | E110: PDFs verified on A4 in Chrome, Edge, Acrobat and one mobile print path; no clipped margins or split questions. | F110: P1 | G110: S | H110: 2 | I110: S24 | J110: In Progress | K110: 2026-10-01. Automated half done: src/lib/pdf/print-qa.integration.test.ts renders a 45-question stress paper (MCQ, long answers, diagrams, OR pairs, 3 sections) in all 3 themes at 9 page-break offsets each (27 layouts), then reads the PDF back with pdf.js. Every page is A4; no question is split across pages; no section title is left alone at a page bottom; no text falls in the 14/12 mm margins. Found and fixed a real bug: section titles were orphaned at the foot of a page (Clean School: Section B on p3, its questions on p4). Fixed with break-after: avoid; the answer key and report also keep their h2 with what follows and never split a table row. Both checks mutation-tested (removing either rule fails the test). Also checked in MuPDF as a second engine. Still manual, owner: open a sample PDF in Acrobat Reader and Edge, and print one from an Android phone onto A4 (set PRINT_QA_OUT to get the exact files).
A111: M22 | B111: F108 | C111: Load & cost test | D111: As an owner I want to know the ceiling so that launch is not a surprise. | E111: Simulate 50 concurrent generations and 20 evaluations; record p95 latency and rupee cost per operation. | F111: P2 | G111: M | H111: 2 | I111: S25 | J111: Done | K111: scripts/load-test.ts (npm run loadtest), not a vitest integration test -- deliberately, since every integration test runs on every npm test and this shared dev DB has shown real instability tonight; a permanent 50-concurrent-connection spike in the routine suite would make that worse. p95 extracted to src/lib/percentiles.ts (5 unit tests). REAL MEASURED CEILING (the feature's actual deliverable, per its own user story): at just 8-20 concurrent requests, the app reliably hit Postgres error EMAXCONNSESSION -- the Supabase session-mode pooler caps the WHOLE APP at 15 concurrent connections, since src/db/connection.ts createDb() opens a new pg.Pool per request. At the AC's literal 50 generations + 20 evaluations, 45/50 and 10/10 failed this way -- a raw driver exception, not a graceful message, so this also fails T22's "daily cap triggers a graceful message, not a crash" clause today. Very likely the same root cause behind this session's repeated vitest worker crashes (see memory note examprep-test-suite-orphan-data). NOT fixed here -- the fix (a shared long-lived pool, and/or Supabase's transaction-mode pooler on port 6543) is architectural, touches every route handler, and is too large/risky to make unsupervised as a side effect of this feature. Flagged as the top pre-launch priority for the owner to pick up next.
...

Sheet 04 Data Model
A1: 04 Data Model — 26 core tables. Build and migrate this before any UI work.
A3: Table | B3: Purpose | C3: Key Columns | D3: Relations | E3: Module
A4: households | B4: Tenant root. One family or one tutor. | C4: id, name, owner_user_id, plan, created_at | D4: -> users, students | E4: M02/M03
A5: users | B5: Anyone who signs in. | C5: id, household_id, email, name, role(parent|student|admin), auth_provider, is_active | D5: -> households | E5: M02
A6: students | B6: The learner profile papers are generated for. | C6: id, household_id, user_id(nullable), name, class, section, roll_no, board, school, target_exams(jsonb) | D6: -> households | E6: M02
A7: subjects | B7: Subject per board and class. | C7: id, board, class, name, code, language, is_active | D7: -> chapters | E7: M04
A8: sources | B8: Textbook a chapter comes from. | C8: id, subject_id, publisher, title, edition, year, file_ref, notes | D8: -> chapters | E8: M04
A9: chapters | B9: Chapter/unit within a subject. | C9: id, subject_id, source_id, no, name, blurb, order_index | D9: -> concepts, chapter_scope | E9: M04
A10: chapter_scope | B10: Explicit IN and OUT syllabus boundary. Prevents out-of-scope generation. | C10: id, chapter_id, kind(IN|OUT), item_text, page_ref | D10: -> chapters | E10: M04
A11: concepts | B11: Smallest trackable learning unit. | C11: id, chapter_id, code, name, description, difficulty_base, idea, rule, example | D11: -> questions, mastery | E11: M04
A12: concept_prereqs | B12: Prerequisite graph between concepts. | C12: concept_id, prereq_concept_id | D12: self-join on concepts | E12: M04
A13: questions | B13: The question bank. | C13: id, concept_id, bloom, difficulty, marks, type, text, text_hash, answer, hint, tags[], diagram_kind, diagram_params(jsonb), language, status(draft|approved|retired), created_by, source_ref | D13: -> options, step_marks | E13: M05
A14: question_options | B14: MCQ / match options. | C14: id, question_id, label, text, is_correct, order_index | D14: -> questions | E14: M05
... A38: scan_detections | B38: F051-F053: one answer the vision model found on a page, its mapping to a question, confidence, position on the page, and review status. | C38: id, attempt_id, student_id, scan_page_id, detected_label, paper_question_id, response_text, selected_option, confidence, bbox, status, confirmed_by_user_id, confirmed_at, created_at | D38: -> attempts, students, scan_pages, paper_questions, users | E38: M10

Sheet 05 API Endpoints
A1: 05 API Endpoints — 38 routes. Auth column is the minimum role; all routes are household-scoped server-side.
A3: Method | B3: Route | C3: Auth | D3: Request | E3: Response | F3: Module
A4: POST | B4: /api/auth/sign-in | C4: Public | D4: email, password | oauth code | E4: session cookie, user | F4: M02
A5: POST | B5: /api/auth/sign-out | C5: User | D5: - | E5: 204 | F5: M02
A6: GET | B6: /api/students | C6: Parent | D6: - | E6: student[] for household | F6: M02
A7: POST | B7: /api/students | C7: Parent | D7: name, class, board, school, roll_no | E7: student | F7: M02
A8: PATCH | B8: /api/students/:id | C8: Parent | D8: partial profile | E8: student | F8: M02
A9: GET | B9: /api/syllabus/subjects | C9: User | D9: board, class | E9: subject[] | F9: M04
A10: GET | B10: /api/syllabus/chapters | C10: User | D10: subject_id | E10: chapter[] with scope counts | F10: M04
A11: GET | B11: /api/syllabus/chapters/:id/scope | C11: User | D11: - | E11: IN[] and OUT[] scope items with page refs | F11: M04
A12: POST | B12: /api/syllabus/chapters/:id/scope | C12: Admin | D12: kind, items[] | E12: created scope items | F12: M04
A13: POST | B13: /api/syllabus/import | C13: Admin | D13: source pdf ref, chapter_id | E13: draft concepts + scope for approval | F13: M04
A14: GET | B14: /api/questions | C14: Admin | D14: filters: concept, bloom, difficulty, type, status | E14: paginated question[] | F14: M05
... A50: GET | B50: /api/scan-pages/:pageId | C50: Signed URL AND session with access | D50: exp, sig | E50: page image (no-store) | F50: M20

Sheet 06 Screens & Routes
A1: 06 Screens and Routes — 24 screens. Reuse the prototype's shell, mastery ring and card components.
A3: Route | B3: Screen | C3: Role | D3: Key Elements | E3: Module
A4: / | B4: Landing / sign-in | C4: Public | D4: Value proposition, sign in, sign up | E4: M02
A5: /onboarding | B5: Setup wizard | C5: Parent | D5: Add student, pick board/class, choose subjects, set exam dates | E5: M02
A6: /home | B6: Parent dashboard | C6: Parent | D6: Subject cards, Delivery Gap trend, priority concepts, next actions, pending uploads | E6: M14
A7: /student | B7: Student home | C7: Student | D7: Mastery rings, today's drill, streak, recent wins | E7: M14
A8: /subjects/:id | B8: Subject overview | C8: Parent | D8: Chapter list with coverage %, tested/untested, weak concept count | E8: M04
A9: /chapters/:id | B9: Chapter detail | C9: Both | D9: Concepts, scope IN/OUT, mastery per concept, generate chapter paper | E9: M04
A10: /generate | B10: Paper generator | C10: Parent | D10: Blueprint picker, chapters, marks/duration, weighting preview, theme | E10: M06
A11: /papers | B11: Paper library | C11: Parent | D11: All generated papers, status (not attempted / attempted / evaluated), re-download | E11: M07
A12: /papers/:id | B12: Paper detail | C12: Parent | D12: Question list, coverage table, download paper + key, start online attempt | E12: M07
A13: /papers/:id/print | B13: Print view | C13: Parent | D13: Print-exact HTML mirror of the PDF with rough-work column | E13: M07
A14: /attempt/:id | B14: Test runner | C14: Student | D14: Timer, section nav, answer inputs, flag question, autosave indicator | E14: M08
... A27: /admin/usage | B27: AI usage & cost | C27: Admin | D27: Tokens, cost by feature and day, rate-limit status, alerts | E27: M19

Sheet 07 AI Layer
A1: 07 AI Function Catalogue — the highest-risk, highest-value tab. Every AI output is a proposal; a human confirms anything that changes a score.
A3: ID | B3: Function | C3: Trigger | D3: Model Tier | E3: Inputs | F3: Output Contract | G3: Guardrails | H3: Fallback When AI Fails
A4: AI-01 | B4: Question generation | C4: Admin asks for N questions on a concept | D4: Strong model (Claude Sonnet/Opus class) | E4: Concept record, chapter IN/OUT scope, source text extract, Bloom, difficulty, marks, 3 exemplar questions | F4: Strict JSON: text, options, answer, hint, step_marks[], bloom, tags | G4: Must cite which IN-scope item it tests; reject if it uses an OUT-scope idea; never invent a formula outside the chapter | H4: Admin writes the question manually; queue stays draft
A5: AI-02 | B5: Distractor quality check | C5: On question save | D5: Cheap model | E5: Question, options, answer | F5: JSON: plausible(bool), issues[] | G5: Flags giveaway distractors and two-correct-answers cases; advisory only, never blocks | H5: Skip check, mark for human review
A6: AI-03 | B6: Duplicate detection | C6: On question save | D6: Embedding model | E6: Question text | F6: Similarity scores vs bank | G6: Warn above 0.90; exact hash match blocks the save | H6: Hash-only comparison
A7: AI-04 | B7: Objective answer normalisation | C7: Auto-scoring | D7: Deterministic code, no AI | E7: Response, expected answer | F7: Match/no-match | G7: Rule-based: case, whitespace, units, symbols, Indian vs international numerals; AI is not used where code suffices | H7: n/a
A8: AI-05 | B8: Subjective answer grading | C8: Evaluation of short/long answers | D8: Strong model | E8: Question, marking scheme steps, expected answer, student response, subject conventions | F8: JSON: marks per step, total, error_type, one-line feedback, confidence | G8: Never final: human confirms. Must justify each step mark. Refuses to grade when the response is unreadable rather than guessing | H8: Item marked 'needs manual marking'
A9: AI-06 | B9: Handwriting transcription | C9: Uploaded scan | D9: Vision model | E9: Page images, expected question numbers | F9: JSON per question: text, confidence, bounding box | G9: Below-threshold confidence must be confirmed by the parent before scoring; Telugu script must be preserved, never romanised | H9: Parent types the answer manually
A10: AI-07 | B10: Error pattern classification | C10: After marks are confirmed | D10: Mid-tier model | E10: Question, response, marks lost, pattern library definitions | F10: Pattern codes with a short rationale | G10: Only picks from the stored pattern library; may return none; cannot invent new patterns | H10: Leave unclassified; surfaces in review
A11: AI-08 | B11: Feedback line writing | C11: Per lost-mark question | D11: Mid-tier model | E11: Question, error type, correct approach | F11: One sentence, max 25 words | G11: Specific and actionable; no praise padding, no shaming; names the concept and the fix | H11: Template feedback from error type
A12: AI-09 | B12: Remediation pack authoring | C12: Concept flagged PRIORITY | D12: Strong model | E12: Concept idea/rule/example, past wrong answers, class level | F12: JSON: refresher (2-3 lines), 2 worked examples with steps, 3 practice questions with answers | G12: Examples must follow the stored marking-scheme format; cached per concept after one human review | H12: Serve existing bank questions with no narrative
A13: AI-10 | B13: Diagnosis narrative | C13: Report generation | D13: Strong model | E13: Evaluation items, pattern hits, habit ratings, tracker history | F13: Report sections: what happened, why, three ranked actions, one parent action | G13: All numbers passed in as data — the model never computes scores; parent action must be a single concrete task | H13: Rule-based template report
A14: AI-11 | B14: Weekly summary | C14: Every 7 active days | D14: Mid-tier model | E14: Week's evaluations, tracker deltas, plan completion | F14: Summary sections + 7-day plan | G14: Plan must draw only from concepts currently flagged; no invented dates | H14: Rule-based summary from tracker deltas
A15: AI-12 | B15: Syllabus scope extraction | C15: Admin uploads a chapter PDF | D15: Strong model + PDF text | E15: Chapter text, existing taxonomy | F15: Draft concept list + IN/OUT scope bullets with page refs | G15: Draft only, admin approves; must quote page numbers; explicitly lists what is OUT of scope | H15: Admin authors scope manually
A16: AI-13 | B16: Per-question worked explanation | C16: Student asks for an explanation on a confirmed result | D16: Strong model (a confidently wrong explanation shown to a child is worse than none)

Sheet 08 Gap Analysis
A1: 08 Gap Analysis — Grok prototype (grok-workspace.zip) vs the target product.
A3: Capability | B3: State in Prototype | C3: Action Required | D3: Reuse | E3: Module | F3: Comment
A4: Project scaffold (TanStack Start, Vite, TS) | B4: Present and working | C4: Keep as-is | D4: Reuse 100% | E4: M01 | F4: Saves ~3 days
A5: UI kit (Tailwind v4 + shadcn/ui, app shell, cards, tabs) | B5: Present, good quality | C5: Extend with print styles and report components | D5: Reuse 90% | E5: M01 | F5: Saves ~2 days
A6: Auth (better-auth, email/password, gates) | B6: Present | C6: Add roles, household, student switching | D6: Reuse 60% | E6: M02 | F6: Roles are the missing piece
A7: Database (Neon/PGlite, Kysely, migration runner) | B7: Present | C7: Replace toy schema with the 26-table model | D7: Reuse 50% | E7: M03 | F7: Plumbing reusable, schema is not
A8: Curriculum data | B8: Hardcoded TypeScript, Class 7 Maths, 15 chapters | C8: Move to DB, add scope IN/OUT, sources, other subjects | D8: Reuse as seed data | E8: M04 | F8: Good seed content; wrong storage layer
A9: Question bank | B9: 75 hardcoded questions, 5 types, Bloom + difficulty + marks | C9: Move to DB, add step marks, language, status, usage history | D9: Reuse as seed data | E9: M05 | F9: Metadata model is already close to right
A10: Scoring (MCQ, true/false, fill-in with normalisation) | B10: Present and reasonable | C10: Extend normalisation, add subjective grading | D10: Reuse 70% | E10: M09 | F10: normalizeAnswer() is a genuinely useful head start
A11: Mastery engine (attempts/correct, thresholds, status) | B11: Present | C11: Replace derived-only model with append-only ledger, add trend, priority rules | D11: Reuse 40% | E11: M12 | F11: Thresholds differ from the coaching spec
A12: Exam runner (mode, size, take, results) | B12: Basic version present | C12: Add timer, autosave, per-question timing, review screen, sections | D12: Reuse 40% | E12: M08 | F12: Currently 5/10/15 question quiz, not a sectioned paper
A13: Practice and Learn routes | B13: Present | C13: Reuse as the remediation delivery surface | D13: Reuse 60% | E13: M13 | F13: Good fit for the drill loop
A14: State (Zustand persist, seeded demo students) | B14: Present | C14: Replace client-seeded mastery with server truth | D14: Replace | E14: M03 | F14: Demo seeding must not survive into production
... A27: AI cost metering and limits | B27: Absent | C27: Build from scratch | D27: New | E27: M19 | F27: Unbounded spend risk without it

Sheet 09 Tech Stack
A1: 09 Technology Decisions — lock these before Phase 1 so nothing is rewritten mid-build.
A3: Layer | B3: Recommendation | C3: Rationale | D3: Alternatives Considered | E3: Note
A4: Framework | B4: TanStack Start (React 19) or Next.js 15 App Router | C4: Prototype already runs TanStack Start; switching costs days for no functional gain. Choose Next.js only if you want its larger ecosystem and hiring pool. | D4: Next.js, Remix | E4: Decide in week 1 and do not revisit
A5: Language | B5: TypeScript strict | C5: Type safety across a large data model is worth the friction. | D5: JavaScript | E5: Locked
A6: Styling | B6: Tailwind CSS v4 + shadcn/ui | C6: Already in the prototype; print stylesheets are straightforward. | D6: MUI, Chakra | E6: Locked
A7: Database | B7: Postgres (Neon or Supabase) | C7: Relational data with heavy joins across students, concepts and evaluations. Supabase adds auth, storage and row-level security in one. | D7: MongoDB, PlanetScale | E7: Supabase recommended if you want storage + RLS bundled
A8: Query layer | B8: Kysely (in prototype) or Drizzle | C8: Typed SQL without ORM magic. Drizzle has better migration ergonomics. | D8: Prisma, raw SQL | E8: Either is fine; do not mix both
A9: Auth | B9: better-auth (prototype) or Supabase Auth | C9: Depends on the database choice. Do not run two auth systems. | D9: Clerk, Auth0 | E9: Follow the DB decision
A10: File storage | B10: Supabase Storage or Cloudflare R2 | C10: Handwriting scans are private, potentially large, and must use signed URLs. | D10: S3, Vercel Blob | E10: Never a public bucket
A11: PDF generation | B11: Playwright/Chromium headless on a Node serverless function, or WeasyPrint on a small worker | C11: HTML-to-PDF gives full CSS control and font embedding, which matters most for Telugu script. | D11: react-pdf, jsPDF | E11: Test Telugu conjuncts before locking this in
A12: AI provider | B12: Anthropic Claude API (generation, grading, vision) with a cheap tier for classification | C12: Long context suits full marking schemes and chapter scope; vision handles handwriting. | D12: OpenAI, Gemini | E12: Keep a provider-agnostic wrapper so a second model is a config change
A13: Background jobs | B13: Inngest or Trigger.dev | C13: PDF rendering, OCR and grading exceed serverless request timeouts and need retries. | D13: Vercel cron, BullMQ | E13: Do not run OCR inside a request handler
A14: Hosting | B14: Vercel | C14: Prototype already targets it; preview deploys per PR are genuinely useful. | D14: Railway, Fly.io | E14: Locked
... A21: Payments | B21: Razorpay | C21: Indian market, UPI, GST-compliant invoicing. | D21: Stripe | E21: Phase 4 only

Sheet 10 Roadmap
A1: 10 Roadmap — change the Project Start Date and every phase date recalculates
A3: Project Start Date | B3: 46280 | C3: Developer-days available per week (velocity) | D3: 4.5 | E3: Assumption: one developer working with an AI coding assistant, 4-5 productive days per week.
A5: Phase | B5: Modules | C5: Goal / Definition of Done | D5: Est. Days | E5: Weeks | F5: Start | G5: End | H5: Exit Criteria
A6: P0 Foundation | B6: M01, M02, M03 | C6: A deployed, authenticated, multi-student skeleton on a real schema. | D6: =SUMIF('02 Module Master'!$C:$C,"P0 Foundation*",'02 Module Master'!$J:$J) | E6: =ROUNDUP(D6/$D$3,0) | F6: =$B$3 | G6: =F6+E6*7 | H6: Parent can sign in, add two students, switch between them; migrations run in CI; preview deploys work.
A7: P1 Core MVP | B7: M04, M05, M06, M07, M08, M09, M12 | C7: Generate a syllabus-correct paper, attempt it, get it marked, see the tracker move. | D7: =SUMIF('02 Module Master'!$C:$C,"P1 Core*",'02 Module Master'!$J:$J) | E7: =ROUNDUP(D7/$D$3,0) | F7: =G6+1 | G7: =F7+E7*7 | H7: A real chapter paper is generated, printed, attempted on screen, auto-evaluated, and the concept tracker updates — end to end without developer intervention.
A8: P2 Diagnostics | B8: M10, M11, M13, M14 | C8: The product's actual differentiator: photo upload, Delivery Gap, remediation, reports. | D8: =SUMIF('02 Module Master'!$C:$C,"P2 Diagnostics*",'02 Module Master'!$J:$J) | E8: =ROUNDUP(D8/$D$3,0) | F8: =G7+1 | G8: =F8+E8*7 | H8: A handwritten paper is photographed, transcribed, confirmed, evaluated, and produces a diagnosis report with Delivery Gap plus an auto-generated remediation drill.
A9: P3 Engagement | B9: M15, M16, M17, M18 | C9: Habit-forming layer plus content self-service and Telugu. | D9: =SUMIF('02 Module Master'!$C:$C,"P3 Engagement*",'02 Module Master'!$J:$J) | E9: =ROUNDUP(D9/$D$3,0) | F9: =G8+1 | G9: =F9+E9*7 | H9: Weekly summary and daily parent action delivered automatically; an admin adds a new chapter and questions without a developer; a Telugu paper prints correctly.
A10: P4 Hardening & Launch | B10: M19, M20, M21, M22 | C10: Safe, measured, legally shippable, and tested against real papers. | D10: =SUMIF('02 Module Master'!$C:$C,"P4 Hardening*",'02 Module Master'!$J:$J) | E10: =ROUNDUP(D10/$D$3,0) | F10: =G9+1 | G10: =F10+E10*7 | H10: AI accuracy >=85% agreement on the 100-answer fixture; consent and data export live; zero cross-household access in the isolation test; three real school papers reproduced in UAT.
C11: TOTAL | D11: =SUM(D6:D10) | E11: =SUM(E6:E10) | G11: =G10
A13: Cut-down option: if you need something usable fast, ship P0 + P1 only (paper generation, on-screen attempt, auto-evaluation, tracker) and defer photo upload. That is roughly the first two phases of the schedule above.
A14: Estimates assume one developer using an AI coding assistant. Two developers do not halve the time; expect roughly 0.65x with parallel module ownership.
A15: Dates above use base effort at the stated velocity. Tab 13 adds a 25% contingency buffer, which pushes the end date out by roughly four months. Plan against tab 13, communicate tab 10.

Sheet 11 Risks
A1: 11 Risk Register — reviewed at every phase gate.
A3: ID | B3: Risk | C3: Probability | D3: Impact | E3: Mitigation | F3: Module
A4: R01 | B4: AI grading of subjective answers is unreliable and a parent loses trust after one bad mark | C4: High | D4: High | E4: Human confirmation is mandatory before any score commits; show AI confidence; run the 100-answer accuracy harness before launch and after every prompt change | F4: M09, M22
A5: R02 | B5: Handwriting OCR fails on real Class 7 handwriting, especially Telugu | C5: High | D5: High | E5: Always keep a typed-entry path; confidence thresholds with image-crop confirmation; treat OCR as an accelerator, never a requirement | F5: M10
A6: R03 | B6: AI generates out-of-syllabus questions and wastes the student's time | C6: Medium | D6: High | E6: Generation is constrained by stored IN/OUT chapter scope with source page refs; automated syllabus-fidelity audit on every paper (F106) | F6: M04, M06
A7: R04 | B7: AI costs scale faster than value as papers and evaluations grow | C7: Medium | D7: Medium | E7: Token metering per call from day one; cheap models for classification; cache remediation packs per concept; hard daily caps | F7: M19
A8: R05 | B8: PDF print output does not match the school's real format, so the paper feels fake | C8: Medium | D8: High | E8: Blueprints derived from actual school papers; UAT reproduces three real papers; print QA across four render paths | F8: M07, M22
A9: R06 | B9: Telugu script renders incorrectly in the PDF (broken conjuncts, tofu boxes) | C9: Medium | D9: High | E9: Embed Noto Sans Telugu / Mallanna and verify a 200-word sample with ottulu and deerghalu before building the Telugu module | F9: M18
A10: R07 | B10: Question bank stays too small, so papers repeat and stop being diagnostic | C10: High | D10: Medium | E10: AI generation with a review queue; usage history prevents recent repeats; target 40+ approved questions per chapter before that chapter goes live | F10: M05, M17
A11: R08 | B11: Scope creep into a full LMS delays the core loop indefinitely | C11: High | D11: High | E11: Tab 01 out-of-scope list is binding; anything new enters the backlog as P3 and does not displace P0/P1 | F11: All
A12: R09 | B12: Child data breach or non-compliance with DPDP Act 2023 | C12: Low | D12: Severe | E12: Consent capture, encryption at rest, signed short-lived URLs, isolation tests on every endpoint, export and delete, audit log — all before any external user | F12: M20
A13: R10 | B13: The parent stops uploading attempts and the loop dies | C13: Medium | D13: High | E13: Make upload a two-minute job: photograph, confirm, done; nudges on WhatsApp; show the tracker moving immediately after each evaluation | F13: M10, M16
A14: R11 | B14: Single-developer dependency; the project stalls if that person is unavailable | C14: Medium | D14: High | E14: Documentation and decision log in-repo from week one; no undocumented prompts; conventional structure a new developer can pick up | F14: M22
... A17: R14 | B17: Vision or LLM provider changes pricing, limits or model availability mid-build | C17: Low | D17: Medium | E17: Provider-agnostic AI wrapper; model choice is configuration; fallback path defined per AI function in tab 07 | F17: M19

Sheet 12 QA & Test Plan
A1: 12 QA and Test Plan — the accuracy tests (T12, T13, T15) matter more than code coverage.
A3: ID | B3: Module | C3: Area | D3: Scenario | E3: Expected Result | F3: Type | G3: Priority
A4: T01 | B4: M02 | C4: Auth & roles | D4: Student account attempts to open the evaluation-override endpoint | E4: 403 from the server, not merely a hidden UI button | F4: Automated | G4: P0
A5: T02 | B5: M02 | C5: Household isolation | D5: Household A requests every endpoint with Household B's IDs | E5: Every request denied; automated sweep across all routes | F5: Automated | G5: P0
A6: T03 | B6: M04 | C6: Scope guard | D6: Generator is asked for a concept marked OUT of scope | E6: Generation refuses with a clear reason; no question produced | F6: Automated | G6: P0
A7: T04 | B7: M05 | C7: Question validation | D7: Save an MCQ with two correct options and one with step marks not summing to the question marks | E7: Both rejected with field-level errors | F7: Automated | G7: P0
A8: T05 | B8: M06 | C8: Blueprint compliance | D8: Generate 20 papers from one blueprint | E8: All 20 match section counts and marks exactly; Bloom mix within +/-5pp or a stated shortfall | F8: Automated | G8: P0
A9: T06 | B9: M06 | C9: Weighted selection | D9: Student with 5 weak, 8 needs-practice, 12 strong concepts generates a paper | E9: Distribution lands near 40/40/20 and the actual split is shown to the parent | F9: Automated | G9: P0
A10: T07 | B10: M06 | C10: Repeat avoidance | D10: Generate three consecutive papers on the same chapter | E10: No question repeats within the configured window unless the bank is exhausted, and exhaustion is reported | F10: Automated | G10: P1
A11: T08 | B11: M07 | C11: Print fidelity | D11: Print the PDF on A4 in Chrome, Edge, Acrobat and a mobile print path | E11: No clipped margins; no question split across a page break; rough-work column present on every working page | F11: Manual | G11: P0
A12: T09 | B12: M07 | C12: Key separation | D12: Student role requests the paper PDF | E12: Answer key is never included and the key endpoint is denied for that role | F12: Automated | G12: P0
A13: T10 | B13: M08 | C13: Autosave & resume | D13: Kill the browser mid-attempt and reopen on another device | E13: All answers preserved; timer continues correctly; no duplicate attempt created | F13: Manual | G13: P0
A14: T11 | B14: M08 | C14: Blank warning | D14: Submit with three unanswered questions | E14: Explicit blank warning listing the question numbers before submission is allowed | F14: Automated | G14: P0
... A25: T22 | B25: M19 | C25: Cost ceiling | D25: Generate 50 papers and 20 evaluations under load | E25: p95 latency and rupee cost per operation recorded; daily cap triggers a graceful message, not a crash | F25: Automated | G25: P2

Sheet 13 Effort Summary
A1: 13 Effort Summary — all figures roll up from tab 03
A3: Assumptions
A4: Developer-days available per week | B4: 4.5 | C4: One developer with an AI coding assistant, allowing for meetings and rework.
A5: Contingency buffer | B5: 0.25 | C5: 25% added for the unknowns that always appear — OCR tuning and print layout in particular.
A6: Blended day rate (INR) | B6: 6000 | C6: Change to your own rate, or set to 0 if you are building it yourself.
A8: By Phase
A9: Phase | B9: Features | C9: Base Days | D9: With Buffer | E9: Calendar Weeks | F9: Indicative Cost (INR)
A10: P0 Foundation | B10: =SUMPRODUCT((LEFT('02 Module Master'!$C$4:$C$25,13)="P0 Foundation")*'02 Module Master'!$I$4:$I$25) | C10: =SUMPRODUCT((LEFT('02 Module Master'!$C$4:$C$25,13)="P0 Foundation")*'02 Module Master'!$J$4:$J$25) | D10: =ROUND(C10*(1+$B$5),0) | E10: =ROUNDUP(D10/$B$4,0) | F10: =D10*$B$6
A11: P1 Core | B11: =SUMPRODUCT((LEFT('02 Module Master'!$C$4:$C$25,7)="P1 Core")*'02 Module Master'!$I$4:$I$25) | C11: =SUMPRODUCT((LEFT('02 Module Master'!$C$4:$C$25,7)="P1 Core")*'02 Module Master'!$J$4:$J$25) | D11: =ROUND(C11*(1+$B$5),0) | E11: =ROUNDUP(D11/$B$4,0) | F11: =D11*$B$6
A12: P2 Diagnostics | B12: =SUMPRODUCT((LEFT('02 Module Master'!$C$4:$C$25,14)="P2 Diagnostics")*'02 Module Master'!$I$4:$I$25) | C12: =SUMPRODUCT((LEFT('02 Module Master'!$C$4:$C$25,14)="P2 Diagnostics")*'02 Module Master'!$J$4:$J$25) | D12: =ROUND(C12*(1+$B$5),0) | E12: =ROUNDUP(D12/$B$4,0) | F12: =D12*$B$6
A13: P3 Engagement | B13: =SUMPRODUCT((LEFT('02 Module Master'!$C$4:$C$25,13)="P3 Engagement")*'02 Module Master'!$I$4:$I$25) | C13: =SUMPRODUCT((LEFT('02 Module Master'!$C$4:$C$25,13)="P3 Engagement")*'02 Module Master'!$J$4:$J$25) | D13: =ROUND(C13*(1+$B$5),0) | E13: =ROUNDUP(D13/$B$4,0) | F13: =D13*$B$6
A14: P4 Hardening | B14: =SUMPRODUCT((LEFT('02 Module Master'!$C$4:$C$25,12)="P4 Hardening")*'02 Module Master'!$I$4:$I$25) | C14: =SUMPRODUCT((LEFT('02 Module Master'!$C$4:$C$25,12)="P4 Hardening")*'02 Module Master'!$J$4:$J$25) | D14: =ROUND(C14*(1+$B$5),0) | E14: =ROUNDUP(D14/$B$4,0) | F14: =D14*$B$6
A15: TOTAL | B15: =B10+B11+B12+B13+B14 | C15: =C10+C11+C12+C13+C14 | D15: =D10+D11+D12+D13+D14 | E15: =E10+E11+E12+E13+E14 | F15: =F10+F11+F12+F13+F14
A17: By Priority
A18: Priority | B18: Features | C18: Base Days | D18: With Buffer | E18: Calendar Weeks | F18: Meaning
A19: P0 | B19: =COUNTIF('03 Feature Backlog'!$F:$F,A19) | C19: =SUMIF('03 Feature Backlog'!$F:$F,A19,'03 Feature Backlog'!$H:$H) | D19: =ROUND(C19*(1+$B$5),0) | E19: =ROUNDUP(D19/$B$4,0) | F19: MVP blocker — the product does not work without it
A20: P1 | B20: =COUNTIF('03 Feature Backlog'!$F:$F,A20) | C20: =SUMIF('03 Feature Backlog'!$F:$F,A20,'03 Feature Backlog'!$H:$H) | D20: =ROUND(C20*(1+$B$5),0) | E20: =ROUNDUP(D20/$B$4,0) | F20: Needed for a usable v1
A21: P2 | B21: =COUNTIF('03 Feature Backlog'!$F:$F,A21) | C21: =SUMIF('03 Feature Backlog'!$F:$F,A21,'03 Feature Backlog'!$H:$H) | D21: =ROUND(C21*(1+$B$5),0) | E21: =ROUNDUP(D21/$B$4,0) | F21: Valuable, can follow launch
A22: P3 | B22: =COUNTIF('03 Feature Backlog'!$F:$F,A22) | C22: =SUMIF('03 Feature Backlog'!$F:$F,A22,'03 Feature Backlog'!$H:$H) | D22: =ROUND(C22*(1+$B$5),0) | E22: =ROUNDUP(D22/$B$4,0) | F22: Later or optional
A23: TOTAL | B23: =SUM(B19:B22) | C23: =SUM(C19:C22) | D23: =SUM(D19:D22) | E23: =SUM(E19:E22)
A25: Recurring running cost (indicative, monthly, single household)
A26: Item | B26: Plan | C26: INR / month | D26: Note
A27: Hosting (Vercel) | B27: Pro | C27: 1700 | D27: Free tier works until background jobs and long PDF renders start
A28: Database (Neon / Supabase) | B28: Launch tier | C28: 2200 | D28: Free tier is adequate for a single family
A29: File storage | B29: Pay as you go | C29: 400 | D29: Handwriting scans; a few GB per year
A30: AI usage | B30: Metered | C30: 3000 | D30: Assumes ~40 papers generated and evaluated per month; verify against tab 07 model tiers
A31: Background jobs | B31: Starter | C31: 0 | D31: Free tier sufficient at this volume
A32: Email | B32: Free / Starter | C32: 0 | D32: Under 3,000 emails per month
A33: Error tracking | B33: Free | C33: 0 | D33: Sentry developer tier
A34: TOTAL / month | C34: =SUM(C27:C33)
A36: All rupee figures are indicative estimates entered by hand, not quotes. Replace them with your actual pricing before using this for a budget decision.

Sheet 14 Competitive Benchmark
A1: 14 Competitive Benchmark — where the white space is, and which P0 modules it justifies
A2: Researched 05 Sep 2026 from the vendors' own sites and independent reviews. Prices are list prices, converted at roughly Rs 88/USD. Verify before quoting.
A4: A. Who is actually in this market
A5: Player | B5: What it is | C5: Price | D5: Reach in India | E5: Closest overlap with you | F5: Where it stops | G5: What it means for your build
A6: CK-12 Flexi | B6: Free AI tutor (US non-profit), maths and science, chat-first. Snap a problem, get a step-by-step solution. Chrome extension, mobile apps, LMS integration. | C6: Free, permanently. Donation and grant funded. | D6: Global, available in India. 1M+ Play Store downloads. | E6: Assesses knowledge state through conversation and adaptive quizzes; predictive estimation of knowledge gaps and mastery; builds a dynamic study plan. | F6: It solves the problem FOR the student. It never marks HER answer. No school syllabus alignment, no printed paper, no parent view. Independent reviews flag overreliance and answers arriving too fast. | G6: Sets the price floor at zero for generic AI homework help. Do not build chat tutoring.
A7: Brilliant | B7: Paid STEM platform, grades 4-12 through adult. Interactive problem-solving, no video lectures. Koji AI tutor built in. | C7: $27.99/mo or ~$13.49/mo annual (~Rs 1,200-2,500/mo). Family plan for 6. Free tier = first chapter only. | D7: Global, sold in India at USD pricing. 10M+ learners. | E7: Tracks concepts mastered and designs practice sets from progress — the same mechanism as your 40/40/20 weighting. | F7: Own curriculum, not CBSE or any school's chapter scope. No exams, no marking, no parent diagnostic, English only, STEM only. | G7: Proves families pay for interactive practice. Proves the mastery-driven practice-set mechanism works.
A8: Khanmigo (Khan Academy) | B8: Socratic AI tutor over Khan Academy's K-12 library. Image upload for maths and science including handwritten work. | C8: $4/mo or $44/yr for learners; free for teachers in 44+ countries. | D8: NOT available to Indian consumers — learner accounts require US residency and a US billing address. | E8: Guides rather than answers; parents can see the child's tutoring sessions; strongest content-safety standards of the AI tutors. | F8: Geographically closed to your market. Its own reviewers note it is not a grading platform — rubrics and scoring at scale are outside its workflow. | G8: The strongest product in the category cannot sell to your customer. That is a real window.
A9: Embibe (Jio) | B9: THE closest competitor. AI exam-prep platform on a 93,000+ concept knowledge graph, Bayesian knowledge tracing, CBSE/ICSE/State boards plus JEE/NEET. Has a separate parents app. | C9: Free tier; premium via Jio. Reliance-backed, $82M+ raised. | D9: India-first, lakhs of students across 497 cities. Samsung Smart TV distribution deal. | E9: Advanced Feedback Analysis explicitly reports knowledge-gaps AND behaviour-gaps, producing academic-quotient and behavioural-quotient vectors per student. This is conceptually your Delivery Gap. | F9: Everything happens inside their app as MCQ tests on their content. It cannot mark a handwritten paper, cannot match one school's paper blueprint, has no printed artefact, and is aimed at the student, not the parent-as-coach. | G9: Read carefully: your central idea is not unique, but your DELIVERY of it is. Differentiate on the paper-and-pen loop, not on the concept.
A10: Snap-solve apps (Doubtnut, Photomath, Gauth, Question.AI) | B10: Photograph a question, receive the solution. Commodity category, now largely absorbed into general AI assistants. | C10: Free with ads, or low-cost subscription. | D10: Very high in India, including Tier 2/3. | E10: Trained Indian students and parents to photograph schoolwork — the exact behaviour M10 depends on. | F10: Answers questions; does not evaluate attempts. Actively works against exam discipline. | G10: De-risks M10 behaviourally. Also a reason to never position yourself as a solver.
A11: Physics Wallah / Unacademy / Vedantu | B11: Live and recorded coaching at scale, mostly competitive exams plus some school boards. | C11: Rs 2,000-25,000 per course. | D11: Very large. PW founders entered the Hurun list in 2026 on the strength of mass-market exam prep. | E11: Test series with rank and percentile analysis. | F11: Content delivery businesses. Analysis is cohort-level percentile, not individual behaviour diagnosis. No handwritten evaluation. | G11: Not a competitor for a Class 7 school-exam diagnostic. Potential distribution partner much later.
A12: BYJU'S / Toppr | B12: Was the category leader. Acquired Toppr in 2021. | C12: n/a | D12: Valuation effectively zero by Oct 2024; under insolvency proceedings in India, with Supreme Court and NCLT matters running through 2026. | E12: Historically claimed adaptive learning paths and a parent-connect app. | F12: Effectively out of the market. | G12: Their collapse removed the biggest incumbent and made parents sceptical of high-pressure edtech. Sell a diagnostic tool, never a course.
A13: A human tutor in Hyderabad | B13: The real incumbent. Marks her paper, knows the school, talks to the parent. | C13: Rs 1,500-6,000 per subject per month. | D13: Universal. | E13: Actually reads handwriting, actually knows the school's paper pattern, and is trusted. | F13: Inconsistent, unrecorded, no cumulative concept history, no cross-paper pattern detection, and cannot be reviewed at 11pm. | G13: THIS is who you price and position against — not the apps.
A14: B. What this changes in the plan (the capability matrix is on tab 15)
A15: # | B15: Finding | C15: Evidence | D15: Action | E15: Affects
A16: 1 | B16: Your core diagnostic idea already exists — at Embibe | C16: Embibe's Advanced Feedback Analysis reports knowledge-gaps and behaviour-gaps and builds behavioural-quotient vectors per student. Do not pitch 'we measure the gap between knowing and scoring' as novel; a funder or a school will find Embibe in one search. | D16: Reposition around the paper-and-pen loop, which Embibe cannot do: her real handwriting, her real school's paper, her real marking scheme. | E16: M11 unchanged; positioning changes
A17: 2 | B17: The moat is the school, not the AI | C17: Every rival owns its own content and asks the student to come to it. You go to the student's actual syllabus, actual textbook edition and actual school paper format. Rows 1-4 of the matrix are where no one scores Yes. | D17: Treat chapter scope records (F016) and the blueprint engine (F027) as the crown jewels. They are boring to build and very hard to copy at scale. | E17: M04, M06 — protect as P0
A18: 3 | B18: Khanmigo's absence from India is a window, not a permanent gap | C18: Khanmigo requires US residency and a US billing address for learner accounts. That is a business decision, not a technical barrier, and it can reverse. | D18: Do not build anything whose only advantage is 'Khanmigo is not here'. Build the things that stay hard even if it arrives. | E18: Strategy, not a module
A19: 4 | B19: Never become a solver | C19: Snap-solve apps are free, ubiquitous and commoditised. Independent reviews already criticise Flexi for closing the loop too fast with an answer. | D19: Enforce it in product: the answer key is a separate PDF and is never exposed to the student role (test T09). Withholding the answer is the feature. | E19: M07 F036, M22 T09
A20: 5 | B20: Price against a tutor, not against an app | C20: Rivals anchor at zero (Flexi), Rs 350/mo (Khanmigo, unavailable), or Rs 1,200-2,500/mo (Brilliant). A Hyderabad subject tutor is Rs 1,500-6,000/mo and is the thing you actually displace. | D20: Target Rs 800-1,500/month per student for all subjects. Tab 13 shows Rs 7,300/month running cost, so break-even is roughly the 6th to 9th paying family. | E20: M21
A21: 6 | B21: BYJU'S has poisoned the well — use it | C21: BYJU'S valuation fell to effectively zero by October 2024 and it is now in insolvency, after years of complaints about aggressive selling to families. | D21: Sell a diagnostic instrument, not a course. No sales calls, no lock-in, monthly billing, visible cancel. Trust is a feature you can win by default. | E21: M21, positioning
A22: 7 | B22: Privacy certification is table stakes, not a differentiator | C22: Brilliant carries a kidSAFE seal; Khanmigo is COPPA/FERPA compliant. You currently have nothing. | D22: Bring M20 forward from Phase 4 into Phase 2 if you intend to onboard any family outside your own. It is cheaper to build in than to retrofit. | E22: M20 — consider re-phasing
A24: C. One-line positioning to test with three real parents
A25: "Every other app teaches your child a concept. This one marks the paper she actually wrote, in her school's format, and tells you which marks she lost because she did not know it — and which she lost because she stopped writing too early."
A28: Sources: ck12.org and info.ck12.org (Flexi); brilliant.org/math and published reviews (pricing); khanmigo.ai/learners (pricing and US-residency requirement); embibe.com and Embibe's AI engineering write-ups (knowledge graph, behaviour-gap analysis); Wikipedia and Tracxn (BYJU'S insolvency status); Hurun 2026 coverage (Physics Wallah scale). All accessed 05 Sep 2026.

Sheet 15 Capability Matrix
A1: 15 Capability Matrix — Yes / Partial / No. Rows where no rival scores Yes are your product.
A2: Ratings are judgements from each vendor's own published material and independent reviews, September 2026. Re-check before any external use.
A4: # | B4: Capability | C4: Flexi | D4: Brilliant | E4: Khanmigo | F4: Embibe | G4: Snap-solve | H4: Human tutor | I4: ExamPrep AI | J4: White space? | K4: Module
A5: 1 | B5: Aligned to one school's actual chapter scope and textbook edition | C5: No | D5: No | E5: No | F5: Partial | G5: No | H5: Yes | I5: Yes | J5: STRONG | K5: M04
A6: 2 | B6: Generates a full paper matching the school's real blueprint and section structure | C6: No | D6: No | E6: No | F6: Partial | G6: No | H6: Partial | I6: Yes | J6: STRONG | K6: M06
A7: 3 | B7: Print-ready A4 paper with rough-work column for a handwritten attempt | C7: No | D7: No | E7: No | F7: No | G7: No | H7: Yes | I7: Yes | J7: STRONG | K7: M07
A8: 4 | B8: Marks a HANDWRITTEN answer against a stored marking scheme with step marks | C8: No | D8: No | E8: No | F8: No | G8: No | H8: Yes | I8: Yes | J8: STRONG | K8: M09, M10
A9: 5 | B9: Separates a knowledge gap from a delivery/behaviour loss on the same question | C9: No | D9: No | E9: No | F9: Yes | G9: No | H9: Partial | I9: Yes | J9: Weak — Embibe does this | K9: M11
A10: 6 | B10: Named behaviour patterns tracked across papers (One-Idea Stop, Blank Retreat...) | C10: No | D10: No | E10: No | F10: Partial | G10: No | H10: Partial | I10: Yes | J10: MODERATE | K10: M11
A11: 7 | B11: Presentation-habit tracking (units, rough work, overwriting, blanks) | C11: No | D11: No | E11: No | F11: No | G11: No | H11: Partial | I11: Yes | J11: STRONG | K11: M11
A12: 8 | B12: Concept-level mastery tracking with trend over repeated attempts | C12: Yes | D12: Yes | E12: Yes | F12: Yes | G12: No | H12: No | I12: Yes | J12: None | K12: M12
A13: 9 | B13: Weak concepts automatically re-weighted into the next paper (40/40/20) | C13: Partial | D13: Yes | E13: Partial | F13: Yes | G13: No | H13: Partial | I13: Yes | J13: None | K13: M06, M12
A14: 10 | B14: Auto-triggered remediation drill when a concept fails twice | C14: Partial | D14: Partial | E14: Partial | F14: Yes | G14: No | H14: Partial | I14: Yes | J14: None | K14: M13
A15: 11 | B15: Parent-facing diagnosis with ONE concrete action per session | C15: No | D15: No | E15: Partial | F15: Partial | G15: No | H15: Yes | I15: Yes | J15: STRONG | K15: M14
A16: 12 | B16: Weekly summary and 7-day study plan for the parent | C16: Partial | D16: No | E16: No | F16: Partial | G16: No | H16: Partial | I16: Yes | J16: MODERATE | K16: M14, M15
... A22: 18 | B22: Child-privacy certification or seal as a trust signal | C22: Partial | D22: Yes | E22: Yes | F22: Partial | G22: No | H22: n/a | I22: Planned | J22: Catch-up needed | K22: M20
B24: Count of capabilities where no rival scores Yes (rows marked STRONG): | J24: =COUNTIF(J5:J22,"STRONG")

Sheet 16 Question Bank Plan
A1: 16 Question Bank Build Plan — 20 questions per concept now, with a costed path to deeper
A2: Launch depth is 20 questions per concept. Every figure below is driven by the yellow input cells, so raising the target later is a single edit here and a single config change in the product (see block G). Concept counts are estimates for CBSE Class 7 — replace them with your real syllabus counts.
A4: A. Inputs (edit the yellow cells)
A6: Target questions per concept | B6: 20 | C6: Your stated target.
A7: AI cost per generated question (INR) | B7: 2 | C7: Grounded generation with source text and few-shot examples, at mid-tier model pricing. Verify against tab 07.
A8: Human review minutes per question | B8: 1.5 | C8: Read, check the answer, check the scope, approve or reject.
A9: Sampled QA rate for Tier A questions | B9: 0.1 | C9: Fraction of auto-approved objective questions that a human spot-checks.
A10: Share of bank eligible for Tier A auto-approve | B10: 0.65 | C10: Objective, 1-2 mark, deterministic answer. The rest need full review.
A11: Productive review hours per day | B11: 5 | C11: One reviewer. Nobody reviews questions for eight hours.
A12: Rejection rate on generated questions | B12: 0.2 | C12: Duplicates, out-of-scope, ambiguous, bad distractors. You pay to generate these too.
A14: B. Volume — CBSE Class 7, all four subjects, at the target depth
A15: Subject | B15: Chapters | C15: Concepts (est.) | D15: Questions needed | E15: To generate (incl. rejects) | F15: Generation cost (INR) | G15: Tier A questions | H15: Tier B questions
A16: Mathematics | B16: 15 | C16: 68 | D16: =C16*$B$6 | E16: =ROUND(D16/(1-$B$12),0) | F16: =E16*$B$7 | G16: =ROUND(D16*$B$10,0) | H16: =D16-G16
A17: Science | B17: 12 | C17: 54 | D17: =C17*$B$6 | E17: =ROUND(D17/(1-$B$12),0) | F17: =E17*$B$7 | G17: =ROUND(D17*$B$10,0) | H17: =D17-G17
A18: Social Studies | B18: 20 | C18: 80 | D18: =C18*$B$6 | E18: =ROUND(D18/(1-$B$12),0) | F18: =E18*$B$7 | G18: =ROUND(D18*$B$10,0) | H18: =D18-G18
A19: Telugu | B19: 16 | C19: 45 | D19: =C19*$B$6 | E19: =ROUND(D19/(1-$B$12),0) | F19: =E19*$B$7 | G19: =ROUND(D19*$B$10,0) | H19: =D19-G19
A20: TOTAL (one class) | B20: =SUM(B16:B19) | C20: =SUM(C16:C19) | D20: =SUM(D16:D19) | E20: =SUM(E16:E19) | F20: =SUM(F16:F19) | G20: =SUM(G16:G19) | H20: =SUM(H16:H19)
A22: C. The real constraint is review time, not AI cost
A23: Review model | B23: Questions fully read | C23: Review minutes | D23: Review hours | E23: Reviewer-days | F23: Verdict
A24: Naive: every question read by a human | B24: =D20 | C24: =B24*$B$8 | D24: =C24/60 | E24: =ROUND(D24/$B$11,0) | F24: Not viable. This is a year of full-time reading for one class.
A25: Tiered: Tier A sampled, Tier B fully reviewed (F117) | B25: =ROUND(G20*$B$9+H20,0) | C25: =B25*$B$8 | D25: =C25/60 | E25: =ROUND(D25/$B$11,0) | F25: Better, still a content operation rather than a feature. Phase it — see block D.
A27: D. Phased depth targets — 20 now, deeper when the loop has proved itself
A28: Phase | B28: Questions per concept | C28: Subjects covered | D28: Concepts | E28: Questions | F28: Tiered reviewer-days | G28: Why this number
A29: Phase 1 (launch) | B29: 20 | C29: Maths + Science | D29: 122 | E29: =B29*D29 | F29: =ROUND((E29*$B$10*$B$9+E29*(1-$B$10))*$B$8/60/$B$11,0) | G29: About 5-7 non-repeating papers per chapter at three difficulty tiers. Enough to run a full term and prove the diagnostic loop is worth feeding.
A30: Phase 2 | B30: 20 | C30: All four subjects | D30: 247 | E30: =B30*D30 | F30: =ROUND((E30*$B$10*$B$9+E30*(1-$B$10))*$B$8/60/$B$11,0) | G30: Same depth, extended to Social Studies and Telugu. Breadth before depth: Mahika sits four subjects, not two.
A31: Phase 3 (year 1 review) | B31: 40 | C31: All four subjects | D31: 247 | E31: =B31*D31 | F31: =ROUND((E31*$B$10*$B$9+E31*(1-$B$10))*$B$8/60/$B$11,0) | G31: Doubles the bank once field data (F118) shows which questions actually discriminate. Retire the weak half of the first 20 as you add the next 20.
A32: Phase 4 (optional growth) | B32: 100 | C32: All four subjects | D32: 247 | E32: =B32*D32 | F32: =ROUND((E32*$B$10*$B$9+E32*(1-$B$10))*$B$8/60/$B$11,0) | G32: Only if the product goes beyond one household. At 100 per concept most Bloom x difficulty cells hold 5+ items and blueprints stop hitting shortfalls.
A34: E. Coverage grid at 20 per concept — concentrate, do not spread
A35: Bloom level | B35: Easy | C35: Hard | D35: Hardest | E35: Row total | F35: Note
A36: Remember | B36: 3 | C36: 1 | E36: =SUM(B36:D36) | F36: Recall has no 'hardest' tier. Leave it empty rather than forcing a question into it.
A37: Understand | B37: 3 | C37: 2 | E37: =SUM(B37:D37) | F37: Section A and B workhorse.
A38: Apply | B38: 2 | C38: 3 | D38: 1 | E38: =SUM(B38:D38) | F38: Heaviest row — most marks in a real CBSE paper sit here.
A39: Analyse | C39: 2 | D39: 1 | E39: =SUM(B39:D39) | F39: Assertion-Reason, multi-statement, match-the-following, error detection.
A40: Evaluate | C40: 1 | E40: =SUM(B40:D40) | F40: Justify and defend. Thin at Class 7.
A41: Create | D41: 1 | E41: =SUM(B41:D41) | F41: Design or construct. Rare below Class 9 — one item is enough.
A42: TOTAL per concept | B42: =SUM(B36:B41) | C42: =SUM(C36:C41) | D42: =SUM(D36:D41) | E42: =SUM(E36:E41)
A43: At 20 per concept only 11 of the 18 grid cells are filled, and most hold 1-3 questions. A blueprint asking for 'Analyse + Hardest' on one specific concept will often find a single candidate — which is fine while the bank is shallow, provided the generator reports the shortfall honestly (F032) and the no-repeat window (F026) is set per term rather than per year. Generation batches target grid cells, not concepts (F115).
A45: F. Decisions this forces
A46: # | B46: Decision | C46: Recommendation
A47: 1 | B47: Who reviews the questions? | C47: You cannot review 50,000 questions yourself. Either accept the tiered model (F117) with sampled QA on objective items, or budget for a part-time subject teacher as a reviewer. Decide before F116 is built, because the pipeline design depends on it.
A48: 2 | B48: Does depth come before breadth? | C48: Settled: breadth first. 20 per concept across Maths and Science at launch, then the same depth across Social Studies and Telugu. Depth increases only after field data shows which questions discriminate between a student who knows the concept and one who does not.
A49: 3 | B49: 'Diary of a Wimpy Kid' style is a legal problem | C49: The characters, the title, and the hand-lettered typeface are Jeff Kinney / Abrams intellectual property. Do not name it, imitate the characters, or use the font. Build a generic 'Doodle Journal' theme instead: ruled notebook paper, hand-drawn stick figures of your own, marker headings, sketchy borders. Same appeal, no exposure. Manga is a genre and is safe to evoke — provided no existing character, logo or series is reproduced.
A50: 4 | B50: Difficulty naming | C50: 'Easy / Hard / Hardest' skips the middle and will push most questions into 'Hard'. Consider 'Easy / Challenging / Toughest' or keep three tiers but calibrate them in writing per subject (F114), so 'Hardest' in Maths and 'Hardest' in Telugu mean comparable things.
A51: 5 | B51: Can the student's difficulty choice override the weak-concept weighting? | C51: No. F119 makes difficulty a ceiling on question selection while the 40% weak/priority weighting always applies. Otherwise a child who always picks Easy quietly stops being diagnosed.
A53: G. Designed to grow — seven commitments that make raising the target a config change, not a rebuild
A54: # | B54: Commitment | C54: What it means in the build | H54: Feature
A55: 1 | B55: Depth target is data, not a constant | C55: Store target_question_count per concept (with a default inherited from subject, then class). Changing 20 to 40 for one chapter is a row update, never a deploy. | H55: F122
A56: 2 | B56: Coverage grid targets are editable | C56: The Bloom x difficulty target matrix in block E lives in a table, per subject and class. A Telugu grammar concept and a Maths geometry concept do not need the same shape. | H56: F114
A57: 3 | B57: Generation tops up, it does not batch | C57: The job is 'bring concept X to its target', computed as target minus current approved count per grid cell. Running it twice is harmless; running it after raising a target simply generates the difference. | H57: F122, F116
A58: 4 | B58: Nothing is ever deleted | C58: Questions move Draft to Approved to Retired. A retired question keeps its history, so a past evaluation and the concept ledger stay intact and auditable years later. | H58: F020, F118
A59: 5 | B59: The repeat window is configurable | C59: At 20 per concept set the no-repeat window to one term. At 100 set it to a year. This is the single setting that decides whether a shallow bank feels shallow. | H59: F026
A60: 6 | B60: Quality improves with volume, automatically | C60: Live stats promote and demote questions. As the bank grows, the weakest early items are flagged and retired instead of diluting the pool. | H60: F118
A61: 7 | B61: Shortfalls are reported, never hidden | C61: When the bank cannot fill a blueprint slot the paper is still produced, with a printed note naming the concept and cell that came up short. That note is also your generation backlog. | H61: F032
A63: Net effect: the bank starts at 20 per concept and about 10 reviewer-days, and can reach 100 per concept without touching a line of generation, selection or paper code. Only the numbers in block A and the target rows in the database change.

Sheet 17 Rollout Sequence
A1: 17 Rollout Sequence — Class 7 Maths first, then Classes 6-12 by demand
A2: Cost and review figures pull from the input cells on tab 16, so changing the depth target there updates this tab too. Concept counts are estimates — replace them as each book is ingested.
A4: A. Source inventory — NCERT Ganita Prakash, Class 7. All 15 chapters accounted for; nothing needs uploading.
A5: File code | B5: Part | C5: Ch | D5: Chapter name | E5: Pages | F5: Format | G5: Status | H5: Concepts (est.) | I5: Note
A6: gegp101 | B6: I | C6: 1 | D6: Large Numbers Around Us | E6: 23 | F6: ZIP of page JPEGs + per-page .txt | G6: READY | H6: 5 | I6: Text layer clean
A7: gegp102 | B7: I | C7: 2 | D7: Arithmetic Expressions | E7: 22 | F7: ZIP of page JPEGs + per-page .txt | G7: READY | H7: 4 | I7: Text layer clean
A8: gegp103 | B8: I | C8: 3 | D8: A Peek Beyond the Point (Decimals) | E8: 35 | F8: True PDF | G8: READY | H8: 8 | I8: Supplied earlier; scope already authored; one paper generated
A9: gegp104 | B9: I | C9: 4 | D9: Expressions Using Letter-Numbers | E9: 25 | F9: True PDF | G9: READY | H9: 5 | I9: Supplied earlier; scope already authored; one paper generated
A10: gegp105 | B10: I | C10: 5 | D10: Parallel and Intersecting Lines | E10: 21 | F10: True PDF | G10: READY | H10: 9 | I10: Supplied earlier; scope already authored; one paper generated
A11: gegp106 | B11: I | C11: 6 | D11: Number Play | E11: 19 | F11: ZIP of page JPEGs + per-page .txt | G11: READY | H11: 4 | I11: Text layer clean
A12: gegp107 | B12: I | C12: 7 | D12: A Tale of Three Intersecting Lines (Triangles) | E12: 27 | F12: ZIP of page JPEGs + per-page .txt | G12: READY | H12: 5 | I12: Text layer clean
A13: gegp108 | B13: I | C13: 8 | D13: Working with Fractions | E13: 30 | F13: ZIP of page JPEGs + per-page .txt | G13: READY | H13: 5 | I13: Text layer clean
A14: gegp201 | B14: II | C14: 1 | D14: Geometric Twins | E14: 23 | F14: ZIP of page JPEGs + per-page .txt | G14: READY | H14: 4 | I14: Text layer clean
A15: gegp202 | B15: II | C15: 2 | D15: Operations with Integers | E15: 23 | F15: ZIP of page JPEGs + per-page .txt | G15: READY | H15: 5 | I15: Text layer clean
A16: gegp203 | B16: II | C16: 3 | D16: Finding Common Ground (HCF / LCM) | E16: 20 | F16: ZIP of page JPEGs + per-page .txt | G16: READY | H16: 4 | I16: Text layer clean
A17: gegp204 | B17: II | C17: 4 | D17: Another Peek Beyond the Point | E17: 30 | F17: ZIP of page JPEGs + per-page .txt | G17: READY | H17: 5 | I17: Builds on Part I Ch 3 — link as prerequisite
... A20: gegp207 | B20: II | C20: 7 | D20: Finding the Unknown | E20: 35 | F20: ZIP of page JPEGs + per-page .txt | G20: READY | H20: 5 | I20: Text layer clean
D21: TOTAL — Class 7 Mathematics | E21: =SUM(E6:E20) | H21: =SUM(H6:H20)
A22: The 12 files in the project folder are NOT corrupt. They are ZIP archives of page JPEGs plus a per-page text layer and a manifest.json, saved with a .pdf extension — which is why every PDF reader rejected them. Renaming to .zip and extracting gives clean, machine-readable text for all 319 pages. Chapters 3, 4 and 5 were supplied separately as real PDFs and their scope records already exist.
A24: B. What launching on Class 7 Maths alone actually costs
A25: Metric | B25: Value | C25: Note
A26: Chapters | B26: =15 | C26: Part I (8) + Part II (7)
A27: Concepts | B27: =$H$21 | C27: Estimated from the inventory above; firm these up during scope authoring (F016)
A28: Questions at target depth | B28: =$H$21*'16 Question Bank Plan'!$B$6 | C28: At the 20-per-concept target set on tab 16
A29: Questions to generate (incl. rejects) | B29: =ROUND(B28/(1-'16 Question Bank Plan'!$B$12),0) | C29: Allows for duplicates, out-of-scope and ambiguous items
A30: AI generation cost (INR) | B30: =B29*'16 Question Bank Plan'!$B$7 | C30: One-off
A31: Human review, tiered model (days) | B31: =ROUND((B28*'16 Question Bank Plan'!$B$10*'16 Question Bank Plan'!$B$9+B28*(1-'16 Question Bank Plan'!$B$10))*'16 Question Bank Plan'!$B$8/60/'16 Question Bank Plan'!$B$11,0) | C31: Tier A sampled, Tier B fully read — F117
A32: Scope authoring (days) | B32: =15*0.5 | C32: About half a day per chapter to write the IN / OUT scope records with page refs
A33: Content work for the entire launch subject is roughly one working week. The bank is not the bottleneck — the product is.
A35: C. Scaling to Classes 6-12 — what the full ambition costs in content
A36: Band | B36: Classes | C36: Subjects | D36: Class-subjects | E36: Concepts each | F36: Total concepts | G36: Questions | H36: Gen cost (INR) | I36: Reviewer-days
A37: Middle — Maths & Science | B37: 6, 7, 8 | C37: Maths, Science | D37: 6 | E37: 65 | F37: =D37*E37 | G37: =F37*'16 Question Bank Plan'!$B$6 | H37: =ROUND(G37/(1-'16 Question Bank Plan'!$B$12),0)*'16 Question Bank Plan'!$B$7 | I37: =ROUND((G37*'16 Question Bank Plan'!$B$10*'16 Question Bank Plan'!$B$9+G37*(1-'16 Question Bank Plan'!$B$10))*'16 Question Bank Plan'!$B$8/60/'16 Question Bank Plan'!$B$11,0)
A38: Middle — Social Studies | B38: 6, 7, 8 | C38: Social Studies | D38: 3 | E38: 80 | F38: =D38*E38 | G38: =F38*'16 Question Bank Plan'!$B$6 | H38: =ROUND(G38/(1-'16 Question Bank Plan'!$B$12),0)*'16 Question Bank Plan'!$B$7 | I38: =ROUND((G38*'16 Question Bank Plan'!$B$10*'16 Question Bank Plan'!$B$9+G38*(1-'16 Question Bank Plan'!$B$10))*'16 Question Bank Plan'!$B$8/60/'16 Question Bank Plan'!$B$11,0)
A39: Middle — Telugu | B39: 6, 7, 8 | C39: Telugu | D39: 3 | E39: 45 | F39: =D39*E39 | G39: =F39*'16 Question Bank Plan'!$B$6 | H39: =ROUND(G39/(1-'16 Question Bank Plan'!$B$12),0)*'16 Question Bank Plan'!$B$7 | I39: =ROUND((G39*'16 Question Bank Plan'!$B$10*'16 Question Bank Plan'!$B$9+G39*(1-'16 Question Bank Plan'!$B$10))*'16 Question Bank Plan'!$B$8/60/'16 Question Bank Plan'!$B$11,0)
A40: Secondary — Maths & Science | B40: 9, 10 | C40: Maths, Science | D40: 4 | E40: 80 | F40: =D40*E40 | G40: =F40*'16 Question Bank Plan'!$B$6 | H40: =ROUND(G40/(1-'16 Question Bank Plan'!$B$12),0)*'16 Question Bank Plan'!$B$7 | I40: =ROUND((G40*'16 Question Bank Plan'!$B$10*'16 Question Bank Plan'!$B$9+G40*(1-'16 Question Bank Plan'!$B$10))*'16 Question Bank Plan'!$B$8/60/'16 Question Bank Plan'!$B$11,0)
A41: Secondary — Social Studies | B41: 9, 10 | C41: Social Studies | D41: 2 | E41: 95 | F41: =D41*E41 | G41: =F41*'16 Question Bank Plan'!$B$6 | H41: =ROUND(G41/(1-'16 Question Bank Plan'!$B$12),0)*'16 Question Bank Plan'!$B$7 | I41: =ROUND((G41*'16 Question Bank Plan'!$B$10*'16 Question Bank Plan'!$B$9+G41*(1-'16 Question Bank Plan'!$B$10))*'16 Question Bank Plan'!$B$8/60/'16 Question Bank Plan'!$B$11,0)
A42: Secondary — Telugu | B42: 9, 10 | C42: Telugu | D42: 2 | E42: 50 | F42: =D42*E42 | G42: =F42*'16 Question Bank Plan'!$B$6 | H42: =ROUND(G42/(1-'16 Question Bank Plan'!$B$12),0)*'16 Question Bank Plan'!$B$7 | I42: =ROUND((G42*'16 Question Bank Plan'!$B$10*'16 Question Bank Plan'!$B$9+G42*(1-'16 Question Bank Plan'!$B$10))*'16 Question Bank Plan'!$B$8/60/'16 Question Bank Plan'!$B$11,0)
A43: Senior — PCM / PCB | B43: 11, 12 | C43: Maths, Physics, Chemistry, Biology | D43: 8 | E43: 110 | F43: =D43*E43 | G43: =F43*'16 Question Bank Plan'!$B$6 | H43: =ROUND(G43/(1-'16 Question Bank Plan'!$B$12),0)*'16 Question Bank Plan'!$B$7 | I43: =ROUND((G43*'16 Question Bank Plan'!$B$10*'16 Question Bank Plan'!$B$9+G43*(1-'16 Question Bank Plan'!$B$10))*'16 Question Bank Plan'!$B$8/60/'16 Question Bank Plan'!$B$11,0)
A44: TOTAL — Classes 6 to 12, all subjects | D44: =SUM(D37:D43) | F44: =SUM(F37:F43) | G44: =SUM(G37:G43) | H44: =SUM(H37:H43) | I44: =SUM(I37:I43)
A45: Content cost per class-subject is roughly constant, so sequence by demand and defensibility, not by cost. Spread across three years this is a part-time content role, not a department.
A47: D. Recommended sequence — follow the student, not the market
A48: Wave | B48: Scope | C48: Why now | D48: Risk if done earlier / later | I48: Trigger to start
A49: W1 | B49: Class 7 Maths | C49: The book is in hand, three chapters already have scope records and generated papers, and Mahika is the live test case. Proves the whole loop end to end on one subject. | D49: Nothing. This is the right starting point. | I49: Now
A50: W2 | B50: Class 7 Science + Social + Telugu | C50: Mahika sits four subjects. A tool covering one of them competes with her notebook, not with a tutor. Breadth beats depth for the first real user. | D50: Skipping this makes the product a maths app and kills the cross-subject pattern detection that is your actual insight (P1-P6 span subjects). | I50: W1 loop working end to end
A51: W3 | B51: Class 8, all subjects | C51: She moves up. A family that starts in Class 7 stays five years if you stay one step ahead of them. Retention beats acquisition at this size. | D51: Jumping to Class 10 instead leaves your only real user behind and forfeits the compounding concept history. | I51: Feb, before the academic year turns
A52: W4 | B52: Class 6, all subjects | C52: Completes middle school. Also unlocks the cross-class prerequisite graph — Class 7 decimals traced back to Class 6 fractions. | D52: Cheap and defensible: fewer competitors chase Class 6 than Class 10. | I52: After W3, or earlier if a second family has a younger child
A53: W5 | B53: Classes 9-10, Maths & Science | C53: Highest willingness to pay because of board pressure. But the most crowded segment, and the tutor you displace is more entrenched. | D53: Entering here first means fighting Physics Wallah and Embibe on their ground with an empty bank. | I53: Only with paying users asking for it
A54: W6 | B54: Classes 11-12 (PCM / PCB) | C54: Largest market, and a different product. Streams, board plus JEE/NEET, far heavier content. | D54: STOP AND RECONSIDER: the parent-marks-the-paper model breaks here. Most parents cannot mark Class 12 Physics. Either the AI grades unsupervised (accuracy risk) or you sell to tutors instead of parents. | I54: Deliberate strategy decision, not a natural next step
A56: E. Five things to build now because they are expensive to retrofit
A57: # | B57: Build now | C57: Why it is cheap now and painful later | I57: Feature
A58: 1 | B58: Chapter identity is (book, part, number) — never number alone | C58: Ganita Prakash Class 7 has TWO chapter 3s, TWO chapter 6s and a 'A Peek Beyond the Point' in Part I answered by 'Another Peek Beyond the Point' in Part II. Any schema keying chapters on a bare number corrupts the moment Part II is loaded. This is not hypothetical — it is in the book you are starting with. | I58: F015
A59: 2 | B59: Class and board are dimensions from day one | C59: Every concept code, question and blueprint carries class and board. Adding Class 8 must be a data load, not a migration. Never hardcode 'Class 7' in a route, a prompt or a PDF header. | I59: F015, F017
A60: 3 | B60: Cross-class prerequisite links | C60: Class 7 Part II Ch 6 explicitly refers back to Grade 6 constructions. Storing that link now is one row; reconstructing it across seven classes later is a project. It is also the capability Embibe markets as tracking gaps across grades. | I60: F018
A61: 4 | B61: Source registry stores the NCERT file code | C61: Record gegp101, gegp207 and so on against each chapter. When NCERT reprints, you know exactly which chapters to re-ingest and which scope records to re-verify. | I61: F017
A62: 5 | B62: An ingestion path for image-plus-text bundles, not just PDFs | C62: The files you already own are ZIPs of page JPEGs with a text sidecar. Build the ingester to handle true PDFs, image bundles and scans from the start; it is the same code path M10 needs for handwriting anyway. | I62: F085, F019
